package com.moat.analytics.mobile.kiip;












final class i
{
  private static int ˊॱ = 1;
  










  private static int ᐝ = 0;
  











  i(String paramString)
  {
    ˊ = false;
    ˏ = false;
    ॱ = false;
    ˎ = 200;
    ˋ = 10;
    ˊ(paramString);
  }
  
  /* Error */
  private void ˊ(String arg1)
  {
    // Byte code:
    //   0: aload_1
    //   1: ifnonnull +4 -> 5
    //   4: return
    //   5: new 55	org/json/JSONObject
    //   8: dup
    //   9: aload_1
    //   10: invokespecial 91	org/json/JSONObject:<init>	(Ljava/lang/String;)V
    //   13: dup
    //   14: astore_1
    //   15: ldc 1
    //   17: ldc 31
    //   19: bipush 59
    //   21: invokestatic 72	com/moat/analytics/mobile/kiip/i:ˎ	(ILjava/lang/String;B)Ljava/lang/String;
    //   24: invokevirtual 82	java/lang/String:intern	()Ljava/lang/String;
    //   27: invokevirtual 94	org/json/JSONObject:getString	(Ljava/lang/String;)Ljava/lang/String;
    //   30: dup
    //   31: astore_2
    //   32: ldc 4
    //   34: ldc 32
    //   36: bipush 66
    //   38: invokestatic 72	com/moat/analytics/mobile/kiip/i:ˎ	(ILjava/lang/String;B)Ljava/lang/String;
    //   41: invokevirtual 82	java/lang/String:intern	()Ljava/lang/String;
    //   44: invokevirtual 81	java/lang/String:equals	(Ljava/lang/Object;)Z
    //   47: istore_3
    //   48: aload_2
    //   49: ldc 4
    //   51: ldc 34
    //   53: bipush 43
    //   55: invokestatic 72	com/moat/analytics/mobile/kiip/i:ˎ	(ILjava/lang/String;B)Ljava/lang/String;
    //   58: invokevirtual 82	java/lang/String:intern	()Ljava/lang/String;
    //   61: invokevirtual 81	java/lang/String:equals	(Ljava/lang/Object;)Z
    //   64: istore 4
    //   66: aload_2
    //   67: ldc 1
    //   69: ldc 36
    //   71: bipush 121
    //   73: invokestatic 72	com/moat/analytics/mobile/kiip/i:ˎ	(ILjava/lang/String;B)Ljava/lang/String;
    //   76: invokevirtual 82	java/lang/String:intern	()Ljava/lang/String;
    //   79: invokevirtual 81	java/lang/String:equals	(Ljava/lang/Object;)Z
    //   82: ifne +8 -> 90
    //   85: goto_w 0 0 2 17
    //   90: goto_w 0 0 2 6
    //   95: iload_3
    //   96: ifne +8 -> 104
    //   99: goto_w 0 0 2 35
    //   104: goto_w 0 0 2 24
    //   109: iload 4
    //   111: ifeq +8 -> 119
    //   114: goto_w 0 0 2 53
    //   119: goto_w 0 0 2 41
    //   124: aload_1
    //   125: invokestatic 71	com/moat/analytics/mobile/kiip/i:ˊ	(Lorg/json/JSONObject;)Z
    //   128: ifne +8 -> 136
    //   131: goto_w 0 0 2 67
    //   136: goto_w 0 0 2 56
    //   141: aload_1
    //   142: invokestatic 74	com/moat/analytics/mobile/kiip/i:ˏ	(Lorg/json/JSONObject;)Z
    //   145: ifne +8 -> 153
    //   148: goto_w 0 0 2 83
    //   153: goto_w 0 0 2 71
    //   158: aload_0
    //   159: iconst_1
    //   160: putfield 59	com/moat/analytics/mobile/kiip/i:ˊ	Z
    //   163: aload_0
    //   164: iload_3
    //   165: putfield 63	com/moat/analytics/mobile/kiip/i:ˏ	Z
    //   168: aload_0
    //   169: iload 4
    //   171: putfield 64	com/moat/analytics/mobile/kiip/i:ॱ	Z
    //   174: aload_0
    //   175: getfield 64	com/moat/analytics/mobile/kiip/i:ॱ	Z
    //   178: ifeq +8 -> 186
    //   181: goto_w 0 0 2 81
    //   186: goto_w 0 0 2 70
    //   191: aload_0
    //   192: iconst_1
    //   193: putfield 63	com/moat/analytics/mobile/kiip/i:ˏ	Z
    //   196: aload_1
    //   197: ldc 1
    //   199: ldc 38
    //   201: bipush 25
    //   203: invokestatic 72	com/moat/analytics/mobile/kiip/i:ˎ	(ILjava/lang/String;B)Ljava/lang/String;
    //   206: invokevirtual 82	java/lang/String:intern	()Ljava/lang/String;
    //   209: invokevirtual 95	org/json/JSONObject:has	(Ljava/lang/String;)Z
    //   212: ifeq +8 -> 220
    //   215: goto_w 0 0 2 79
    //   220: goto_w 0 0 2 68
    //   225: aload_1
    //   226: ldc 1
    //   228: ldc 38
    //   230: bipush 25
    //   232: invokestatic 72	com/moat/analytics/mobile/kiip/i:ˎ	(ILjava/lang/String;B)Ljava/lang/String;
    //   235: invokevirtual 82	java/lang/String:intern	()Ljava/lang/String;
    //   238: invokevirtual 92	org/json/JSONObject:getInt	(Ljava/lang/String;)I
    //   241: dup
    //   242: istore_2
    //   243: bipush 100
    //   245: if_icmplt +8 -> 253
    //   248: goto_w 0 0 2 79
    //   253: goto_w 0 0 2 67
    //   258: iload_2
    //   259: sipush 1000
    //   262: if_icmpgt +8 -> 270
    //   265: goto_w 0 0 2 94
    //   270: goto_w 0 0 2 82
    //   275: aload_0
    //   276: iload_2
    //   277: putfield 62	com/moat/analytics/mobile/kiip/i:ˎ	I
    //   280: aload_1
    //   281: ldc 1
    //   283: ldc 35
    //   285: bipush 24
    //   287: invokestatic 72	com/moat/analytics/mobile/kiip/i:ˎ	(ILjava/lang/String;B)Ljava/lang/String;
    //   290: invokevirtual 82	java/lang/String:intern	()Ljava/lang/String;
    //   293: invokevirtual 95	org/json/JSONObject:has	(Ljava/lang/String;)Z
    //   296: ifeq +8 -> 304
    //   299: goto_w 0 0 2 91
    //   304: goto_w 0 0 2 80
    //   309: aload_0
    //   310: aload_1
    //   311: ldc 1
    //   313: ldc 35
    //   315: bipush 24
    //   317: invokestatic 72	com/moat/analytics/mobile/kiip/i:ˎ	(ILjava/lang/String;B)Ljava/lang/String;
    //   320: invokevirtual 82	java/lang/String:intern	()Ljava/lang/String;
    //   323: invokevirtual 92	org/json/JSONObject:getInt	(Ljava/lang/String;)I
    //   326: putfield 61	com/moat/analytics/mobile/kiip/i:ˋ	I
    //   329: aload_1
    //   330: invokestatic 73	com/moat/analytics/mobile/kiip/i:ˎ	(Lorg/json/JSONObject;)Z
    //   333: ifeq +8 -> 341
    //   336: goto_w 0 0 2 87
    //   341: goto_w 0 0 2 75
    //   346: invokestatic 69	com/moat/analytics/mobile/kiip/MoatAnalytics:getInstance	()Lcom/moat/analytics/mobile/kiip/MoatAnalytics;
    //   349: checkcast 44	com/moat/analytics/mobile/kiip/j
    //   352: iconst_1
    //   353: putfield 66	com/moat/analytics/mobile/kiip/j:ˏ	Z
    //   356: return
    //   357: astore_1
    //   358: aload_0
    //   359: iconst_0
    //   360: putfield 59	com/moat/analytics/mobile/kiip/i:ˊ	Z
    //   363: aload_0
    //   364: iconst_0
    //   365: putfield 63	com/moat/analytics/mobile/kiip/i:ˏ	Z
    //   368: aload_0
    //   369: sipush 200
    //   372: putfield 62	com/moat/analytics/mobile/kiip/i:ˎ	I
    //   375: aload_1
    //   376: invokestatic 75	com/moat/analytics/mobile/kiip/o:ॱ	(Ljava/lang/Exception;)V
    //   379: return
    //   380: getstatic 65	com/moat/analytics/mobile/kiip/i:ᐝ	I
    //   383: bipush 91
    //   385: iadd
    //   386: dup
    //   387: sipush 128
    //   390: irem
    //   391: putstatic 60	com/moat/analytics/mobile/kiip/i:ˊॱ	I
    //   394: iconst_2
    //   395: irem
    //   396: ifne +8 -> 404
    //   399: goto_w 0 0 0 10
    //   404: goto_w -1 -1 -2 -53
    //   409: goto_w -1 -1 -2 -58
    //   414: getstatic 60	com/moat/analytics/mobile/kiip/i:ˊॱ	I
    //   417: bipush 51
    //   419: iadd
    //   420: dup
    //   421: sipush 128
    //   424: irem
    //   425: putstatic 65	com/moat/analytics/mobile/kiip/i:ᐝ	I
    //   428: iconst_2
    //   429: irem
    //   430: ifeq +8 -> 438
    //   433: goto_w 0 0 0 10
    //   438: goto_w -1 -1 -1 9
    //   443: goto_w -1 -1 -1 4
    //   448: getstatic 65	com/moat/analytics/mobile/kiip/i:ᐝ	I
    //   451: bipush 117
    //   453: iadd
    //   454: dup
    //   455: sipush 128
    //   458: irem
    //   459: putstatic 60	com/moat/analytics/mobile/kiip/i:ˊॱ	I
    //   462: iconst_2
    //   463: irem
    //   464: ifne +8 -> 472
    //   467: goto_w 0 0 0 10
    //   472: goto_w -1 -1 -1 42
    //   477: goto_w -1 -1 -1 37
    //   482: getstatic 60	com/moat/analytics/mobile/kiip/i:ˊॱ	I
    //   485: bipush 59
    //   487: iadd
    //   488: dup
    //   489: sipush 128
    //   492: irem
    //   493: putstatic 65	com/moat/analytics/mobile/kiip/i:ᐝ	I
    //   496: iconst_2
    //   497: irem
    //   498: ifeq +8 -> 506
    //   501: goto_w 0 0 0 10
    //   506: goto_w -1 -1 -1 25
    //   511: goto_w -1 -1 -1 20
    //   516: getstatic 65	com/moat/analytics/mobile/kiip/i:ᐝ	I
    //   519: bipush 55
    //   521: iadd
    //   522: dup
    //   523: sipush 128
    //   526: irem
    //   527: putstatic 60	com/moat/analytics/mobile/kiip/i:ˊॱ	I
    //   530: iconst_2
    //   531: irem
    //   532: ifne +8 -> 540
    //   535: goto_w 0 0 0 10
    //   540: goto_w -1 -1 -1 25
    //   545: goto_w -1 -1 -1 20
    //   550: getstatic 65	com/moat/analytics/mobile/kiip/i:ᐝ	I
    //   553: bipush 69
    //   555: iadd
    //   556: dup
    //   557: sipush 128
    //   560: irem
    //   561: putstatic 60	com/moat/analytics/mobile/kiip/i:ˊॱ	I
    //   564: iconst_2
    //   565: irem
    //   566: ifne +8 -> 574
    //   569: goto_w 0 0 1 -115
    //   574: goto_w 0 0 1 -126
    //   579: invokestatic 69	com/moat/analytics/mobile/kiip/MoatAnalytics:getInstance	()Lcom/moat/analytics/mobile/kiip/MoatAnalytics;
    //   582: checkcast 44	com/moat/analytics/mobile/kiip/j
    //   585: iconst_1
    //   586: putfield 66	com/moat/analytics/mobile/kiip/j:ˏ	Z
    //   589: return
    //   590: tableswitch	default:+-466->124, 0:+-210->380
    //   608: iconst_1
    //   609: goto_w -1 -1 -1 -19
    //   614: iconst_0
    //   615: goto_w -1 -1 -1 -25
    //   620: tableswitch	default:+-496->124, 1:+-511->109
    //   640: iconst_0
    //   641: goto_w -1 -1 -1 -21
    //   646: iconst_1
    //   647: goto_w -1 -1 -1 -27
    //   652: lookupswitch	default:+-528->124, 20:+-456->196
    //   672: bipush 20
    //   674: goto_w -1 -1 -1 -22
    //   679: bipush 34
    //   681: goto_w -1 -1 -1 -29
    //   686: tableswitch	default:+-545->141, 0:+-490->196
    //   704: iconst_0
    //   705: goto_w -1 -1 -1 -19
    //   710: iconst_1
    //   711: goto_w -1 -1 -1 -25
    //   716: lookupswitch	default:+-558->158, 74:+-520->196
    //   736: bipush 74
    //   738: goto_w -1 -1 -1 -22
    //   743: bipush 48
    //   745: goto_w -1 -1 -1 -29
    //   750: tableswitch	default:+-336->414, 1:+-554->196
    //   768: iconst_1
    //   769: goto_w -1 -1 -1 -19
    //   774: iconst_0
    //   775: goto_w -1 -1 -1 -25
    //   780: tableswitch	default:+-555->225, 0:+-500->280
    //   800: iconst_0
    //   801: goto_w -1 -1 -1 -21
    //   806: iconst_1
    //   807: goto_w -1 -1 -1 -27
    //   812: lookupswitch	default:+-532->280, 56:+-364->448
    //   832: bipush 66
    //   834: goto_w -1 -1 -1 -22
    //   839: bipush 56
    //   841: goto_w -1 -1 -1 -29
    //   846: lookupswitch	default:+-566->280, 75:+-364->482
    //   864: bipush 52
    //   866: goto_w -1 -1 -1 -20
    //   871: bipush 75
    //   873: goto_w -1 -1 -1 -27
    //   878: tableswitch	default:+-362->516, 1:+-549->329
    //   896: iconst_1
    //   897: goto_w -1 -1 -1 -19
    //   902: iconst_0
    //   903: goto_w -1 -1 -1 -25
    //   908: lookupswitch	default:+-552->356, 71:+-358->550
    //   928: bipush 1
    //   930: goto_w -1 -1 -1 -22
    //   935: bipush 71
    //   937: goto_w -1 -1 -1 -29
    //   942: tableswitch	default:+-596->346, 1:+-363->579
    //   960: iconst_0
    //   961: goto_w -1 -1 -1 -19
    //   966: iconst_1
    //   967: goto_w -1 -1 -1 -25
    // Line number table:
    //   Java source line #52	-> byte code offset #0
    //   Java source line #56	-> byte code offset #5
    //   Java source line #58	-> byte code offset #14
    //   Java source line #59	-> byte code offset #31
    //   Java source line #60	-> byte code offset #48
    //   Java source line #62	-> byte code offset #66
    //   Java source line #63	-> byte code offset #124
    //   Java source line #64	-> byte code offset #158
    //   Java source line #65	-> byte code offset #163
    //   Java source line #66	-> byte code offset #168
    //   Java source line #67	-> byte code offset #174
    //   Java source line #68	-> byte code offset #191
    //   Java source line #72	-> byte code offset #196
    //   Java source line #73	-> byte code offset #225
    //   Java source line #74	-> byte code offset #242
    //   Java source line #75	-> byte code offset #275
    //   Java source line #78	-> byte code offset #280
    //   Java source line #79	-> byte code offset #309
    //   Java source line #81	-> byte code offset #329
    //   Java source line #82	-> byte code offset #346
    //   Java source line #84	-> byte code offset #357
    //   Java source line #85	-> byte code offset #358
    //   Java source line #86	-> byte code offset #363
    //   Java source line #87	-> byte code offset #368
    //   Java source line #88	-> byte code offset #375
    //   Java source line #82	-> byte code offset #579
    // Exception table:
    //   from	to	target	type
    //   5	95	357	java/lang/Exception
    //   124	141	357	java/lang/Exception
    //   141	158	357	java/lang/Exception
    //   158	191	357	java/lang/Exception
    //   191	196	357	java/lang/Exception
    //   196	225	357	java/lang/Exception
    //   225	258	357	java/lang/Exception
    //   275	280	357	java/lang/Exception
    //   280	309	357	java/lang/Exception
    //   309	329	357	java/lang/Exception
    //   329	346	357	java/lang/Exception
    //   346	356	357	java/lang/Exception
    //   579	590	357	java/lang/Exception
  }
  
  /* Error */
  private static boolean ˊ(org.json.JSONObject arg0)
  {
    // Byte code:
    //   0: bipush 16
    //   2: getstatic 56	android/os/Build$VERSION:SDK_INT	I
    //   5: if_icmple +8 -> 13
    //   8: goto_w 0 0 0 -86
    //   13: goto_w 0 0 0 -97
    //   18: iconst_1
    //   19: ireturn
    //   20: aload_0
    //   21: ldc 1
    //   23: ldc 37
    //   25: bipush 62
    //   27: invokestatic 72	com/moat/analytics/mobile/kiip/i:ˎ	(ILjava/lang/String;B)Ljava/lang/String;
    //   30: invokevirtual 82	java/lang/String:intern	()Ljava/lang/String;
    //   33: invokevirtual 95	org/json/JSONObject:has	(Ljava/lang/String;)Z
    //   36: ifeq +8 -> 44
    //   39: goto_w 0 0 0 -84
    //   44: goto_w 0 0 0 -96
    //   49: aload_0
    //   50: ldc 1
    //   52: ldc 37
    //   54: bipush 62
    //   56: invokestatic 72	com/moat/analytics/mobile/kiip/i:ˎ	(ILjava/lang/String;B)Ljava/lang/String;
    //   59: invokevirtual 82	java/lang/String:intern	()Ljava/lang/String;
    //   62: invokevirtual 93	org/json/JSONObject:getJSONArray	(Ljava/lang/String;)Lorg/json/JSONArray;
    //   65: astore_0
    //   66: iconst_0
    //   67: istore_1
    //   68: aload_0
    //   69: invokevirtual 90	org/json/JSONArray:length	()I
    //   72: istore_2
    //   73: iload_1
    //   74: iload_2
    //   75: if_icmpge +8 -> 83
    //   78: goto_w 0 0 0 -91
    //   83: goto_w 0 0 0 -103
    //   88: aload_0
    //   89: iload_1
    //   90: invokevirtual 88	org/json/JSONArray:getInt	(I)I
    //   93: getstatic 56	android/os/Build$VERSION:SDK_INT	I
    //   96: if_icmpne +8 -> 104
    //   99: goto_w 0 0 0 -80
    //   104: goto_w 0 0 0 -92
    //   109: iconst_1
    //   110: ireturn
    //   111: iinc 1 1
    //   114: goto_w -1 -1 -1 -41
    //   119: iconst_0
    //   120: ireturn
    //   121: pop
    //   122: iconst_1
    //   123: ireturn
    //   124: getstatic 65	com/moat/analytics/mobile/kiip/i:ᐝ	I
    //   127: bipush 69
    //   129: iadd
    //   130: dup
    //   131: sipush 128
    //   134: irem
    //   135: putstatic 60	com/moat/analytics/mobile/kiip/i:ˊॱ	I
    //   138: iconst_2
    //   139: irem
    //   140: ifne +8 -> 148
    //   143: goto_w 0 0 0 -92
    //   148: goto_w 0 0 0 -104
    //   153: iconst_1
    //   154: ireturn
    //   155: tableswitch	default:+-31->124, 0:+-135->20
    //   172: iconst_0
    //   173: goto_w -1 -1 -1 -18
    //   178: iconst_1
    //   179: goto_w -1 -1 -1 -24
    //   184: lookupswitch	default:+-135->49, 86:+-65->119
    //   204: bipush 86
    //   206: goto_w -1 -1 -1 -22
    //   211: bipush 77
    //   213: goto_w -1 -1 -1 -29
    //   218: lookupswitch	default:+-99->119, 60:+-130->88
    //   236: bipush 71
    //   238: goto_w -1 -1 -1 -20
    //   243: bipush 60
    //   245: goto_w -1 -1 -1 -27
    //   250: lookupswitch	default:+-139->111, 14:+-141->109
    //   268: bipush 26
    //   270: goto_w -1 -1 -1 -20
    //   275: bipush 14
    //   277: goto_w -1 -1 -1 -27
    //   282: lookupswitch	default:+-264->18, 63:+-129->153
    //   300: bipush 39
    //   302: goto_w -1 -1 -1 -20
    //   307: bipush 63
    //   309: goto_w -1 -1 -1 -27
    // Line number table:
    //   Java source line #94	-> byte code offset #0
    //   Java source line #95	-> byte code offset #18
    //   Java source line #97	-> byte code offset #20
    //   Java source line #98	-> byte code offset #49
    //   Java source line #99	-> byte code offset #66
    //   Java source line #100	-> byte code offset #88
    //   Java source line #101	-> byte code offset #93
    //   Java source line #102	-> byte code offset #109
    //   Java source line #99	-> byte code offset #111
    //   Java source line #106	-> byte code offset #119
    //   Java source line #107	-> byte code offset #121
    //   Java source line #108	-> byte code offset #122
    //   Java source line #95	-> byte code offset #153
    // Exception table:
    //   from	to	target	type
    //   0	18	121	java/lang/Exception
    //   20	49	121	java/lang/Exception
    //   49	73	121	java/lang/Exception
    //   88	109	121	java/lang/Exception
  }
  
  /* Error */
  private static boolean ˏ(org.json.JSONObject arg0)
  {
    // Byte code:
    //   0: aload_0
    //   1: ldc 1
    //   3: ldc 33
    //   5: bipush 47
    //   7: invokestatic 72	com/moat/analytics/mobile/kiip/i:ˎ	(ILjava/lang/String;B)Ljava/lang/String;
    //   10: invokevirtual 82	java/lang/String:intern	()Ljava/lang/String;
    //   13: invokevirtual 95	org/json/JSONObject:has	(Ljava/lang/String;)Z
    //   16: ifeq +8 -> 24
    //   19: goto_w 0 0 0 -65
    //   24: goto_w 0 0 0 -76
    //   29: invokestatic 76	com/moat/analytics/mobile/kiip/p:ˎ	()Lcom/moat/analytics/mobile/kiip/p$b;
    //   32: invokevirtual 77	com/moat/analytics/mobile/kiip/p$b:ˋ	()Ljava/lang/String;
    //   35: astore_1
    //   36: aload_0
    //   37: ldc 1
    //   39: ldc 33
    //   41: bipush 47
    //   43: invokestatic 72	com/moat/analytics/mobile/kiip/i:ˎ	(ILjava/lang/String;B)Ljava/lang/String;
    //   46: invokevirtual 82	java/lang/String:intern	()Ljava/lang/String;
    //   49: invokevirtual 93	org/json/JSONObject:getJSONArray	(Ljava/lang/String;)Lorg/json/JSONArray;
    //   52: astore_0
    //   53: iconst_0
    //   54: istore_2
    //   55: aload_0
    //   56: invokevirtual 90	org/json/JSONArray:length	()I
    //   59: istore_3
    //   60: iload_2
    //   61: iload_3
    //   62: if_icmpge +8 -> 70
    //   65: goto_w 0 0 0 -78
    //   70: goto_w 0 0 0 -90
    //   75: aload_0
    //   76: iload_2
    //   77: invokevirtual 89	org/json/JSONArray:getString	(I)Ljava/lang/String;
    //   80: aload_1
    //   81: invokevirtual 80	java/lang/String:contentEquals	(Ljava/lang/CharSequence;)Z
    //   84: ifeq +8 -> 92
    //   87: goto_w 0 0 0 -69
    //   92: goto_w 0 0 0 -80
    //   97: iconst_1
    //   98: ireturn
    //   99: iinc 2 1
    //   102: goto_w -1 -1 -1 -42
    //   107: goto_w 0 0 0 8
    //   112: invokestatic 75	com/moat/analytics/mobile/kiip/o:ॱ	(Ljava/lang/Exception;)V
    //   115: iconst_0
    //   116: ireturn
    //   117: getstatic 60	com/moat/analytics/mobile/kiip/i:ˊॱ	I
    //   120: bipush 115
    //   122: iadd
    //   123: dup
    //   124: sipush 128
    //   127: irem
    //   128: putstatic 65	com/moat/analytics/mobile/kiip/i:ᐝ	I
    //   131: iconst_2
    //   132: irem
    //   133: ifeq +8 -> 141
    //   136: goto_w 0 0 0 10
    //   141: goto_w -1 -1 -1 -66
    //   146: goto_w -1 -1 -1 -71
    //   151: getstatic 60	com/moat/analytics/mobile/kiip/i:ˊॱ	I
    //   154: bipush 47
    //   156: iadd
    //   157: dup
    //   158: sipush 128
    //   161: irem
    //   162: putstatic 65	com/moat/analytics/mobile/kiip/i:ᐝ	I
    //   165: iconst_2
    //   166: irem
    //   167: ifeq +8 -> 175
    //   170: goto_w 0 0 0 10
    //   175: goto_w -1 -1 -1 -78
    //   180: goto_w -1 -1 -1 -83
    //   185: tableswitch	default:+-78->107, 1:+-156->29
    //   204: iconst_0
    //   205: goto_w -1 -1 -1 -20
    //   210: iconst_1
    //   211: goto_w -1 -1 -1 -26
    //   216: lookupswitch	default:+-109->107, 34:+-99->117
    //   236: bipush 56
    //   238: goto_w -1 -1 -1 -22
    //   243: bipush 34
    //   245: goto_w -1 -1 -1 -29
    //   250: tableswitch	default:+-99->151, 0:+-151->99
    //   268: iconst_0
    //   269: goto_w -1 -1 -1 -19
    //   274: iconst_1
    //   275: goto_w -1 -1 -1 -25
    // Line number table:
    //   Java source line #114	-> byte code offset #0
    //   Java source line #115	-> byte code offset #29
    //   Java source line #116	-> byte code offset #36
    //   Java source line #117	-> byte code offset #53
    //   Java source line #118	-> byte code offset #75
    //   Java source line #119	-> byte code offset #97
    //   Java source line #117	-> byte code offset #99
    //   Java source line #124	-> byte code offset #112
    //   Java source line #126	-> byte code offset #115
    // Exception table:
    //   from	to	target	type
    //   0	29	112	java/lang/Exception
    //   29	60	112	java/lang/Exception
    //   75	97	112	java/lang/Exception
  }
  
  /* Error */
  private static boolean ˎ(org.json.JSONObject arg0)
  {
    // Byte code:
    //   0: aload_0
    //   1: ldc 1
    //   3: ldc 30
    //   5: iconst_3
    //   6: invokestatic 72	com/moat/analytics/mobile/kiip/i:ˎ	(ILjava/lang/String;B)Ljava/lang/String;
    //   9: invokevirtual 82	java/lang/String:intern	()Ljava/lang/String;
    //   12: invokevirtual 95	org/json/JSONObject:has	(Ljava/lang/String;)Z
    //   15: ifeq +8 -> 23
    //   18: goto_w 0 0 0 -99
    //   23: goto_w 0 0 0 -111
    //   28: invokestatic 76	com/moat/analytics/mobile/kiip/p:ˎ	()Lcom/moat/analytics/mobile/kiip/p$b;
    //   31: invokevirtual 77	com/moat/analytics/mobile/kiip/p$b:ˋ	()Ljava/lang/String;
    //   34: astore_1
    //   35: aload_0
    //   36: ldc 1
    //   38: ldc 30
    //   40: iconst_3
    //   41: invokestatic 72	com/moat/analytics/mobile/kiip/i:ˎ	(ILjava/lang/String;B)Ljava/lang/String;
    //   44: invokevirtual 82	java/lang/String:intern	()Ljava/lang/String;
    //   47: invokevirtual 93	org/json/JSONObject:getJSONArray	(Ljava/lang/String;)Lorg/json/JSONArray;
    //   50: astore_0
    //   51: iconst_0
    //   52: istore_2
    //   53: aload_0
    //   54: invokevirtual 90	org/json/JSONArray:length	()I
    //   57: istore_3
    //   58: iload_2
    //   59: iload_3
    //   60: if_icmpge +8 -> 68
    //   63: goto_w 0 0 0 -113
    //   68: goto_w 0 0 0 -124
    //   73: aload_0
    //   74: iload_2
    //   75: invokevirtual 89	org/json/JSONArray:getString	(I)Ljava/lang/String;
    //   78: aload_1
    //   79: invokevirtual 80	java/lang/String:contentEquals	(Ljava/lang/CharSequence;)Z
    //   82: ifeq +8 -> 90
    //   85: goto_w 0 0 0 -103
    //   90: goto_w 0 0 0 -114
    //   95: iconst_1
    //   96: ireturn
    //   97: iinc 2 1
    //   100: goto_w -1 -1 -1 -42
    //   105: goto_w 0 0 0 8
    //   110: invokestatic 75	com/moat/analytics/mobile/kiip/o:ॱ	(Ljava/lang/Exception;)V
    //   113: iconst_0
    //   114: ireturn
    //   115: getstatic 65	com/moat/analytics/mobile/kiip/i:ᐝ	I
    //   118: bipush 73
    //   120: iadd
    //   121: dup
    //   122: sipush 128
    //   125: irem
    //   126: putstatic 60	com/moat/analytics/mobile/kiip/i:ˊॱ	I
    //   129: iconst_2
    //   130: irem
    //   131: ifne +8 -> 139
    //   134: goto_w 0 0 0 10
    //   139: goto_w -1 -1 -1 -111
    //   144: goto_w -1 -1 -1 -116
    //   149: lookupswitch	default:+-44->105, 23:+-34->115
    //   168: bipush 55
    //   170: goto_w -1 -1 -1 -21
    //   175: bipush 23
    //   177: goto_w -1 -1 -1 -28
    //   182: tableswitch	default:+-109->73, 1:+-77->105
    //   200: iconst_1
    //   201: goto_w -1 -1 -1 -19
    //   206: iconst_0
    //   207: goto_w -1 -1 -1 -25
    //   212: tableswitch	default:+-115->97, 1:+-117->95
    //   232: iconst_0
    //   233: goto_w -1 -1 -1 -21
    //   238: iconst_1
    //   239: goto_w -1 -1 -1 -27
    // Line number table:
    //   Java source line #131	-> byte code offset #0
    //   Java source line #132	-> byte code offset #28
    //   Java source line #133	-> byte code offset #35
    //   Java source line #134	-> byte code offset #51
    //   Java source line #135	-> byte code offset #73
    //   Java source line #136	-> byte code offset #95
    //   Java source line #134	-> byte code offset #97
    //   Java source line #141	-> byte code offset #110
    //   Java source line #143	-> byte code offset #113
    // Exception table:
    //   from	to	target	type
    //   0	28	110	java/lang/Exception
    //   28	58	110	java/lang/Exception
    //   73	95	110	java/lang/Exception
  }
  
  final boolean ˊ()
  {
    return ˏ;
  }
  
  final boolean ˎ() {
    return ॱ;
  }
  
  final int ˋ() {
    return ˎ;
  }
  
  final int ॱ() {
    return ˋ;
  }
  
  final int ˏ() {
    if (ˊ) return t.c.ॱ; return t.c.ˊ;
  }
  


































































































































































































































































































































































































































































































































































































































































































































































































































































  private static char ʽ = 5; private static char[] ʻ = { 115, 97, 50, 98, 99, 51, 52, 49, 56, 57, 102, 48, 54, 100, 101, 53, 111, 110, 105, 112, 108, 116, 117, 118, 119 };
  private int ˋ;
  private int ˎ;
  private boolean ॱ;
  private boolean ˏ;
  private boolean ˊ;
  
  /* Error */
  private static String ˎ(int arg0, String arg1, byte arg2)
  {
    // Byte code:
    //   0: aload 1
    //   2: invokevirtual 83	java/lang/String:toCharArray	()[C
    //   5: checkcast 39	[C
    //   8: astore 1
    //   10: iload_2
    //   11: istore 4
    //   13: getstatic 57	com/moat/analytics/mobile/kiip/i:ʻ	[C
    //   16: astore_2
    //   17: iload_0
    //   18: istore_3
    //   19: getstatic 58	com/moat/analytics/mobile/kiip/i:ʽ	C
    //   22: istore_0
    //   23: iload_3
    //   24: newarray char
    //   26: astore 5
    //   28: iload_3
    //   29: iconst_2
    //   30: irem
    //   31: ifeq +8 -> 39
    //   34: goto_w 0 0 1 -52
    //   39: goto_w 0 0 1 -63
    //   44: iinc 3 -1
    //   47: aload 5
    //   49: iload_3
    //   50: aload_1
    //   51: iload_3
    //   52: caload
    //   53: iload 4
    //   55: isub
    //   56: i2c
    //   57: castore
    //   58: iload_3
    //   59: iconst_1
    //   60: if_icmple +8 -> 68
    //   63: goto_w 0 0 1 -49
    //   68: goto_w 0 0 1 -60
    //   73: iconst_0
    //   74: istore 6
    //   76: iload 6
    //   78: iload_3
    //   79: if_icmpge +8 -> 87
    //   82: goto_w 0 0 1 -35
    //   87: goto_w 0 0 1 -47
    //   92: aload_1
    //   93: iload 6
    //   95: caload
    //   96: istore 7
    //   98: aload_1
    //   99: iload 6
    //   101: iconst_1
    //   102: iadd
    //   103: caload
    //   104: istore 8
    //   106: iload 7
    //   108: iload 8
    //   110: if_icmpne +8 -> 118
    //   113: goto_w 0 0 1 -34
    //   118: goto_w 0 0 1 -46
    //   123: aload 5
    //   125: iload 6
    //   127: iload 7
    //   129: iload 4
    //   131: isub
    //   132: i2c
    //   133: castore
    //   134: aload 5
    //   136: iload 6
    //   138: iconst_1
    //   139: iadd
    //   140: iload 8
    //   142: iload 4
    //   144: isub
    //   145: i2c
    //   146: castore
    //   147: goto_w 0 0 0 -23
    //   152: iload 7
    //   154: iload_0
    //   155: invokestatic 84	me/kiip/internal/c/a:a	(II)I
    //   158: istore 9
    //   160: iload 7
    //   162: iload_0
    //   163: invokestatic 86	me/kiip/internal/c/a:b	(II)I
    //   166: istore 7
    //   168: iload 8
    //   170: iload_0
    //   171: invokestatic 84	me/kiip/internal/c/a:a	(II)I
    //   174: istore 10
    //   176: iload 8
    //   178: iload_0
    //   179: invokestatic 86	me/kiip/internal/c/a:b	(II)I
    //   182: istore 8
    //   184: iload 7
    //   186: iload 8
    //   188: if_icmpne +8 -> 196
    //   191: goto_w 0 0 1 -81
    //   196: goto_w 0 0 1 -92
    //   201: iload 9
    //   203: iload_0
    //   204: invokestatic 87	me/kiip/internal/c/a:c	(II)I
    //   207: istore 9
    //   209: iload 10
    //   211: iload_0
    //   212: invokestatic 87	me/kiip/internal/c/a:c	(II)I
    //   215: istore 10
    //   217: iload 9
    //   219: iload 7
    //   221: iload_0
    //   222: invokestatic 85	me/kiip/internal/c/a:a	(III)I
    //   225: istore 9
    //   227: iload 10
    //   229: iload 8
    //   231: iload_0
    //   232: invokestatic 85	me/kiip/internal/c/a:a	(III)I
    //   235: istore 7
    //   237: aload 5
    //   239: iload 6
    //   241: aload_2
    //   242: iload 9
    //   244: caload
    //   245: castore
    //   246: aload 5
    //   248: iload 6
    //   250: iconst_1
    //   251: iadd
    //   252: aload_2
    //   253: iload 7
    //   255: caload
    //   256: castore
    //   257: goto_w 0 0 0 123
    //   262: iload 9
    //   264: iload 10
    //   266: if_icmpne +8 -> 274
    //   269: goto_w 0 0 1 -126
    //   274: goto_w 0 0 1 118
    //   279: iload 7
    //   281: iload_0
    //   282: invokestatic 87	me/kiip/internal/c/a:c	(II)I
    //   285: istore 7
    //   287: iload 8
    //   289: iload_0
    //   290: invokestatic 87	me/kiip/internal/c/a:c	(II)I
    //   293: istore 8
    //   295: iload 9
    //   297: iload 7
    //   299: iload_0
    //   300: invokestatic 85	me/kiip/internal/c/a:a	(III)I
    //   303: istore 9
    //   305: iload 10
    //   307: iload 8
    //   309: iload_0
    //   310: invokestatic 85	me/kiip/internal/c/a:a	(III)I
    //   313: istore 7
    //   315: aload 5
    //   317: iload 6
    //   319: aload_2
    //   320: iload 9
    //   322: caload
    //   323: castore
    //   324: aload 5
    //   326: iload 6
    //   328: iconst_1
    //   329: iadd
    //   330: aload_2
    //   331: iload 7
    //   333: caload
    //   334: castore
    //   335: goto_w 0 0 0 45
    //   340: iload 9
    //   342: iload 8
    //   344: iload_0
    //   345: invokestatic 85	me/kiip/internal/c/a:a	(III)I
    //   348: istore 9
    //   350: iload 10
    //   352: iload 7
    //   354: iload_0
    //   355: invokestatic 85	me/kiip/internal/c/a:a	(III)I
    //   358: istore 7
    //   360: aload 5
    //   362: iload 6
    //   364: aload_2
    //   365: iload 9
    //   367: caload
    //   368: castore
    //   369: aload 5
    //   371: iload 6
    //   373: iconst_1
    //   374: iadd
    //   375: aload_2
    //   376: iload 7
    //   378: caload
    //   379: castore
    //   380: iinc 6 2
    //   383: goto_w -1 -1 -2 -51
    //   388: new 52	java/lang/String
    //   391: dup
    //   392: aload 5
    //   394: invokespecial 79	java/lang/String:<init>	([C)V
    //   397: areturn
    //   398: getstatic 60	com/moat/analytics/mobile/kiip/i:ˊॱ	I
    //   401: bipush 99
    //   403: iadd
    //   404: dup
    //   405: sipush 128
    //   408: irem
    //   409: putstatic 65	com/moat/analytics/mobile/kiip/i:ᐝ	I
    //   412: iconst_2
    //   413: irem
    //   414: ifeq +8 -> 422
    //   417: goto_w 0 0 0 10
    //   422: goto_w -1 -1 -2 -122
    //   427: goto_w -1 -1 -2 -127
    //   432: getstatic 60	com/moat/analytics/mobile/kiip/i:ˊॱ	I
    //   435: bipush 125
    //   437: iadd
    //   438: dup
    //   439: sipush 128
    //   442: irem
    //   443: putstatic 65	com/moat/analytics/mobile/kiip/i:ᐝ	I
    //   446: iconst_2
    //   447: irem
    //   448: ifeq +8 -> 456
    //   451: goto_w 0 0 0 -20
    //   456: goto_w 0 0 0 -32
    //   461: iconst_0
    //   462: istore 6
    //   464: goto_w -1 -1 -2 124
    //   469: tableswitch	default:+-71->398, 1:+-411->58
    //   488: iconst_1
    //   489: goto_w -1 -1 -1 -20
    //   494: iconst_0
    //   495: goto_w -1 -1 -1 -26
    //   500: tableswitch	default:+-112->388, 0:+-68->432
    //   520: iconst_1
    //   521: goto_w -1 -1 -1 -21
    //   526: iconst_0
    //   527: goto_w -1 -1 -1 -27
    //   532: lookupswitch	default:+-440->92, 85:+-144->388
    //   552: bipush 85
    //   554: goto_w -1 -1 -1 -22
    //   559: bipush 99
    //   561: goto_w -1 -1 -1 -29
    //   566: lookupswitch	default:+-443->123, 35:+-414->152
    //   584: bipush 35
    //   586: goto_w -1 -1 -1 -20
    //   591: bipush 24
    //   593: goto_w -1 -1 -1 -27
    //   598: tableswitch	default:+-397->201, 1:+-336->262
    //   616: iconst_1
    //   617: goto_w -1 -1 -1 -19
    //   622: iconst_0
    //   623: goto_w -1 -1 -1 -25
    //   628: lookupswitch	default:+-349->279, 49:+-288->340
    //   648: bipush 49
    //   650: goto_w -1 -1 -1 -22
    //   655: bipush 46
    //   657: goto_w -1 -1 -1 -29
    //   662: lookupswitch	default:+-201->461, 34:+-589->73
    //   680: bipush 34
    //   682: goto_w -1 -1 -1 -20
    //   687: bipush 82
    //   689: goto_w -1 -1 -1 -27
    // Line number table:
    //   Java source line #201	-> byte code offset #0
    //   Java source line #202	-> byte code offset #17
    //   Java source line #203	-> byte code offset #19
    //   Java source line #207	-> byte code offset #23
    //   Java source line #210	-> byte code offset #28
    //   Java source line #212	-> byte code offset #44
    //   Java source line #213	-> byte code offset #47
    //   Java source line #216	-> byte code offset #58
    //   Java source line #218	-> byte code offset #73
    //   Java source line #222	-> byte code offset #92
    //   Java source line #223	-> byte code offset #98
    //   Java source line #226	-> byte code offset #106
    //   Java source line #228	-> byte code offset #123
    //   Java source line #229	-> byte code offset #134
    //   Java source line #234	-> byte code offset #152
    //   Java source line #235	-> byte code offset #160
    //   Java source line #236	-> byte code offset #168
    //   Java source line #237	-> byte code offset #176
    //   Java source line #240	-> byte code offset #184
    //   Java source line #242	-> byte code offset #201
    //   Java source line #243	-> byte code offset #209
    //   Java source line #245	-> byte code offset #217
    //   Java source line #246	-> byte code offset #227
    //   Java source line #248	-> byte code offset #237
    //   Java source line #249	-> byte code offset #246
    //   Java source line #253	-> byte code offset #262
    //   Java source line #255	-> byte code offset #279
    //   Java source line #256	-> byte code offset #287
    //   Java source line #258	-> byte code offset #295
    //   Java source line #259	-> byte code offset #305
    //   Java source line #261	-> byte code offset #315
    //   Java source line #262	-> byte code offset #324
    //   Java source line #270	-> byte code offset #340
    //   Java source line #271	-> byte code offset #350
    //   Java source line #273	-> byte code offset #360
    //   Java source line #274	-> byte code offset #369
    //   Java source line #218	-> byte code offset #380
    //   Java source line #280	-> byte code offset #388
    //   Java source line #218	-> byte code offset #461
  }
}
