package com.moat.analytics.mobile.kiip;

import android.graphics.Rect;
import android.location.Location;
import android.view.View;
import java.util.Comparator;
import java.util.HashMap;
import java.util.Map;
import org.json.JSONObject;

final class y
{
  y() {}
  
  /* Error */
  final void ˎ(String arg1, View arg2)
  {
    // Byte code:
    //   0: goto_w 0 0 0 5
    //   5: new 69	java/util/HashMap
    //   8: dup
    //   9: invokespecial 179	java/util/HashMap:<init>	()V
    //   12: astore_3
    //   13: ldc 30
    //   15: astore 4
    //   17: iconst_0
    //   18: istore 5
    //   20: aload_2
    //   21: ifnull +8 -> 29
    //   24: goto_w 0 0 8 -41
    //   29: goto_w 0 0 8 -53
    //   34: aload_2
    //   35: astore 11
    //   37: getstatic 80	android/os/Build$VERSION:SDK_INT	I
    //   40: bipush 17
    //   42: if_icmplt +8 -> 50
    //   45: goto_w 0 0 8 -27
    //   50: goto_w 0 0 8 -38
    //   55: getstatic 84	com/moat/analytics/mobile/kiip/a:ˊ	Ljava/lang/ref/WeakReference;
    //   58: ifnull +8 -> 66
    //   61: goto_w 0 0 8 -2
    //   66: goto_w 0 0 8 -14
    //   71: getstatic 84	com/moat/analytics/mobile/kiip/a:ˊ	Ljava/lang/ref/WeakReference;
    //   74: invokevirtual 171	java/lang/ref/WeakReference:get	()Ljava/lang/Object;
    //   77: checkcast 31	android/app/Activity
    //   80: dup
    //   81: astore 12
    //   83: ifnull +8 -> 91
    //   86: goto_w 0 0 9 13
    //   91: goto_w 0 0 9 1
    //   96: new 40	android/util/DisplayMetrics
    //   99: dup
    //   100: invokespecial 118	android/util/DisplayMetrics:<init>	()V
    //   103: astore 13
    //   105: aload 12
    //   107: invokevirtual 102	android/app/Activity:getWindowManager	()Landroid/view/WindowManager;
    //   110: invokeinterface 184 1 0
    //   115: aload 13
    //   117: invokevirtual 119	android/view/Display:getRealMetrics	(Landroid/util/DisplayMetrics;)V
    //   120: aload 13
    //   122: goto_w 0 0 0 21
    //   127: aload 11
    //   129: invokevirtual 122	android/view/View:getContext	()Landroid/content/Context;
    //   132: invokevirtual 103	android/content/Context:getResources	()Landroid/content/res/Resources;
    //   135: invokevirtual 104	android/content/res/Resources:getDisplayMetrics	()Landroid/util/DisplayMetrics;
    //   138: goto_w 0 0 0 5
    //   143: astore 6
    //   145: aload_2
    //   146: astore 11
    //   148: getstatic 80	android/os/Build$VERSION:SDK_INT	I
    //   151: bipush 19
    //   153: if_icmplt +8 -> 161
    //   156: goto_w 0 0 8 -17
    //   161: goto_w 0 0 8 -29
    //   166: aload 11
    //   168: ifnull +8 -> 176
    //   171: goto_w 0 0 9 8
    //   176: goto_w 0 0 8 -4
    //   181: aload 11
    //   183: invokevirtual 132	android/view/View:isAttachedToWindow	()Z
    //   186: ifeq +8 -> 194
    //   189: goto_w 0 0 9 25
    //   194: goto_w 0 0 9 14
    //   199: iconst_1
    //   200: goto_w 0 0 0 56
    //   205: iconst_0
    //   206: goto_w 0 0 0 50
    //   211: aload 11
    //   213: ifnull +8 -> 221
    //   216: goto_w 0 0 9 39
    //   221: goto_w 0 0 9 27
    //   226: aload 11
    //   228: invokevirtual 130	android/view/View:getWindowToken	()Landroid/os/IBinder;
    //   231: ifnull +8 -> 239
    //   234: goto_w 0 0 9 61
    //   239: goto_w 0 0 9 49
    //   244: iconst_1
    //   245: goto_w 0 0 0 11
    //   250: iconst_0
    //   251: goto_w 0 0 0 5
    //   256: istore 7
    //   258: aload_2
    //   259: dup
    //   260: astore 11
    //   262: ifnull +8 -> 270
    //   265: goto_w 0 0 9 70
    //   270: goto_w 0 0 9 58
    //   275: aload 11
    //   277: invokevirtual 131	android/view/View:hasWindowFocus	()Z
    //   280: ifeq +8 -> 288
    //   283: goto_w 0 0 9 92
    //   288: goto_w 0 0 9 80
    //   293: iconst_1
    //   294: goto_w 0 0 0 11
    //   299: iconst_0
    //   300: goto_w 0 0 0 5
    //   305: istore 8
    //   307: aload_2
    //   308: dup
    //   309: astore 11
    //   311: ifnull +8 -> 319
    //   314: goto_w 0 0 9 101
    //   319: goto_w 0 0 9 89
    //   324: aload 11
    //   326: invokevirtual 133	android/view/View:isShown	()Z
    //   329: ifne +8 -> 337
    //   332: goto_w 0 0 9 123
    //   337: goto_w 0 0 9 111
    //   342: iconst_1
    //   343: goto_w 0 0 0 11
    //   348: iconst_0
    //   349: goto_w 0 0 0 5
    //   354: istore 9
    //   356: aload_2
    //   357: dup
    //   358: astore 11
    //   360: ifnonnull +8 -> 368
    //   363: goto_w 0 0 9 -124
    //   368: goto_w 0 0 9 120
    //   373: fconst_0
    //   374: goto_w 0 0 0 15
    //   379: aload 11
    //   381: invokestatic 143	com/moat/analytics/mobile/kiip/y:ˊ	(Landroid/view/View;)F
    //   384: goto_w 0 0 0 5
    //   389: fstore 10
    //   391: aload_3
    //   392: ldc 8
    //   394: aload 6
    //   396: getfield 81	android/util/DisplayMetrics:density	F
    //   399: invokestatic 157	java/lang/Float:valueOf	(F)Ljava/lang/Float;
    //   402: invokeinterface 195 3 0
    //   407: pop
    //   408: aload_3
    //   409: ldc 9
    //   411: invokestatic 141	com/moat/analytics/mobile/kiip/p:ॱ	()D
    //   414: invokestatic 155	java/lang/Double:valueOf	(D)Ljava/lang/Double;
    //   417: invokeinterface 195 3 0
    //   422: pop
    //   423: aload_3
    //   424: ldc 6
    //   426: aload_1
    //   427: invokeinterface 195 3 0
    //   432: pop
    //   433: aload_3
    //   434: ldc 14
    //   436: iload 7
    //   438: ifeq +8 -> 446
    //   441: goto_w 0 0 9 89
    //   446: goto_w 0 0 9 78
    //   451: iconst_1
    //   452: goto_w 0 0 0 11
    //   457: iconst_0
    //   458: goto_w 0 0 0 5
    //   463: invokestatic 160	java/lang/Integer:valueOf	(I)Ljava/lang/Integer;
    //   466: invokeinterface 195 3 0
    //   471: pop
    //   472: aload_3
    //   473: ldc 13
    //   475: iload 8
    //   477: ifeq +8 -> 485
    //   480: goto_w 0 0 9 86
    //   485: goto_w 0 0 9 75
    //   490: iconst_1
    //   491: goto_w 0 0 0 11
    //   496: iconst_0
    //   497: goto_w 0 0 0 5
    //   502: invokestatic 160	java/lang/Integer:valueOf	(I)Ljava/lang/Integer;
    //   505: invokeinterface 195 3 0
    //   510: pop
    //   511: aload_3
    //   512: ldc 15
    //   514: iload 9
    //   516: ifeq +8 -> 524
    //   519: goto_w 0 0 9 88
    //   524: goto_w 0 0 9 76
    //   529: iconst_1
    //   530: goto_w 0 0 0 11
    //   535: iconst_0
    //   536: goto_w 0 0 0 5
    //   541: invokestatic 160	java/lang/Integer:valueOf	(I)Ljava/lang/Integer;
    //   544: invokeinterface 195 3 0
    //   549: pop
    //   550: aload_3
    //   551: ldc 20
    //   553: fload 10
    //   555: invokestatic 157	java/lang/Float:valueOf	(F)Ljava/lang/Float;
    //   558: invokeinterface 195 3 0
    //   563: pop
    //   564: aload 6
    //   566: dup
    //   567: astore 11
    //   569: getfield 83	android/util/DisplayMetrics:widthPixels	I
    //   572: istore 12
    //   574: aload 11
    //   576: getfield 82	android/util/DisplayMetrics:heightPixels	I
    //   579: istore 13
    //   581: new 34	android/graphics/Rect
    //   584: dup
    //   585: iconst_0
    //   586: iconst_0
    //   587: iload 12
    //   589: iload 13
    //   591: invokespecial 105	android/graphics/Rect:<init>	(IIII)V
    //   594: astore_1
    //   595: aload_2
    //   596: dup
    //   597: astore 12
    //   599: ifnull +8 -> 607
    //   602: goto_w 0 0 9 40
    //   607: goto_w 0 0 9 29
    //   612: aload 12
    //   614: invokestatic 148	com/moat/analytics/mobile/kiip/y:ॱ	(Landroid/view/View;)Landroid/graphics/Rect;
    //   617: goto_w 0 0 0 21
    //   622: new 34	android/graphics/Rect
    //   625: dup
    //   626: iconst_0
    //   627: iconst_0
    //   628: iconst_0
    //   629: iconst_0
    //   630: invokespecial 105	android/graphics/Rect:<init>	(IIII)V
    //   633: goto_w 0 0 0 5
    //   638: astore 10
    //   640: aload_2
    //   641: aload 10
    //   643: iload 7
    //   645: iload 8
    //   647: iload 9
    //   649: istore_2
    //   650: istore 7
    //   652: istore 13
    //   654: astore 12
    //   656: astore 11
    //   658: new 53	com/moat/analytics/mobile/kiip/y$a
    //   661: dup
    //   662: invokespecial 150	com/moat/analytics/mobile/kiip/y$a:<init>	()V
    //   665: astore 8
    //   667: aload 12
    //   669: dup
    //   670: astore 12
    //   672: invokevirtual 112	android/graphics/Rect:width	()I
    //   675: aload 12
    //   677: invokevirtual 108	android/graphics/Rect:height	()I
    //   680: imul
    //   681: istore 9
    //   683: aload 11
    //   685: ifnull +8 -> 693
    //   688: goto_w 0 0 8 -5
    //   693: goto_w 0 0 8 -17
    //   698: iload 13
    //   700: ifeq +8 -> 708
    //   703: goto_w 0 0 9 20
    //   708: goto_w 0 0 9 8
    //   713: iload 7
    //   715: ifeq +8 -> 723
    //   718: goto_w 0 0 9 40
    //   723: goto_w 0 0 9 29
    //   728: iload_2
    //   729: ifne +8 -> 737
    //   732: goto_w 0 0 9 67
    //   737: goto_w 0 0 9 55
    //   742: iload 9
    //   744: ifle +8 -> 752
    //   747: goto_w 0 0 9 87
    //   752: goto_w 0 0 9 76
    //   757: new 34	android/graphics/Rect
    //   760: dup
    //   761: iconst_0
    //   762: iconst_0
    //   763: iconst_0
    //   764: iconst_0
    //   765: invokespecial 105	android/graphics/Rect:<init>	(IIII)V
    //   768: astore_2
    //   769: aload 11
    //   771: aload_2
    //   772: invokevirtual 124	android/view/View:getGlobalVisibleRect	(Landroid/graphics/Rect;)Z
    //   775: ifeq +8 -> 783
    //   778: goto_w 0 0 9 92
    //   783: goto_w 0 0 9 81
    //   788: aload_2
    //   789: dup
    //   790: astore 12
    //   792: invokevirtual 112	android/graphics/Rect:width	()I
    //   795: aload 12
    //   797: invokevirtual 108	android/graphics/Rect:height	()I
    //   800: imul
    //   801: dup
    //   802: istore 7
    //   804: iload 9
    //   806: if_icmpge +8 -> 814
    //   809: goto_w 0 0 9 97
    //   814: goto_w 0 0 9 86
    //   819: ldc 5
    //   821: aconst_null
    //   822: ldc 3
    //   824: invokestatic 136	com/moat/analytics/mobile/kiip/b:ˏ	(Ljava/lang/String;Ljava/lang/Object;Ljava/lang/String;)V
    //   827: goto_w 0 0 0 5
    //   832: new 70	java/util/HashSet
    //   835: dup
    //   836: invokespecial 180	java/util/HashSet:<init>	()V
    //   839: astore 12
    //   841: aload 11
    //   843: invokevirtual 128	android/view/View:getRootView	()Landroid/view/View;
    //   846: instanceof 43
    //   849: ifeq +8 -> 857
    //   852: goto_w 0 0 9 90
    //   857: goto_w 0 0 9 79
    //   862: aload 8
    //   864: aload_2
    //   865: putfield 96	com/moat/analytics/mobile/kiip/y$a:ˊ	Landroid/graphics/Rect;
    //   868: aload_2
    //   869: aload 11
    //   871: aload 12
    //   873: invokestatic 145	com/moat/analytics/mobile/kiip/y:ˏ	(Landroid/graphics/Rect;Landroid/view/View;Ljava/util/HashSet;)Z
    //   876: dup
    //   877: istore 11
    //   879: ifeq +8 -> 887
    //   882: goto_w 0 0 9 101
    //   887: goto_w 0 0 9 89
    //   892: aload 8
    //   894: dconst_1
    //   895: putfield 98	com/moat/analytics/mobile/kiip/y$a:ˎ	D
    //   898: goto_w 0 0 0 5
    //   903: iload 11
    //   905: ifne +8 -> 913
    //   908: goto_w 0 0 9 110
    //   913: goto_w 0 0 9 99
    //   918: aload_2
    //   919: aload 12
    //   921: invokestatic 142	com/moat/analytics/mobile/kiip/y:ˊ	(Landroid/graphics/Rect;Ljava/util/HashSet;)I
    //   924: dup
    //   925: istore_2
    //   926: ifle +8 -> 934
    //   929: goto_w 0 0 9 125
    //   934: goto_w 0 0 9 114
    //   939: aload 8
    //   941: iload_2
    //   942: i2d
    //   943: iload 7
    //   945: i2d
    //   946: ddiv
    //   947: putfield 98	com/moat/analytics/mobile/kiip/y$a:ˎ	D
    //   950: goto_w 0 0 0 5
    //   955: iload 7
    //   957: iload_2
    //   958: isub
    //   959: istore_2
    //   960: aload 8
    //   962: iload_2
    //   963: i2d
    //   964: iload 9
    //   966: i2d
    //   967: ddiv
    //   968: putfield 97	com/moat/analytics/mobile/kiip/y$a:ˋ	D
    //   971: goto_w 0 0 0 5
    //   976: aload 8
    //   978: astore_2
    //   979: aload_0
    //   980: getfield 92	com/moat/analytics/mobile/kiip/y:ˏ	Lorg/json/JSONObject;
    //   983: ifnull +8 -> 991
    //   986: goto_w 0 0 9 104
    //   991: goto_w 0 0 9 93
    //   996: aload_2
    //   997: getfield 97	com/moat/analytics/mobile/kiip/y$a:ˋ	D
    //   1000: aload_0
    //   1001: getfield 88	com/moat/analytics/mobile/kiip/y:ˊ	Lcom/moat/analytics/mobile/kiip/y$a;
    //   1004: getfield 97	com/moat/analytics/mobile/kiip/y$a:ˋ	D
    //   1007: dcmpl
    //   1008: ifne +8 -> 1016
    //   1011: goto_w 0 0 9 120
    //   1016: goto_w 0 0 9 108
    //   1021: aload_2
    //   1022: getfield 96	com/moat/analytics/mobile/kiip/y$a:ˊ	Landroid/graphics/Rect;
    //   1025: aload_0
    //   1026: getfield 88	com/moat/analytics/mobile/kiip/y:ˊ	Lcom/moat/analytics/mobile/kiip/y$a;
    //   1029: getfield 96	com/moat/analytics/mobile/kiip/y$a:ˊ	Landroid/graphics/Rect;
    //   1032: invokevirtual 107	android/graphics/Rect:equals	(Ljava/lang/Object;)Z
    //   1035: ifeq +8 -> 1043
    //   1038: goto_w 0 0 9 -128
    //   1043: goto_w 0 0 9 117
    //   1048: aload_2
    //   1049: getfield 98	com/moat/analytics/mobile/kiip/y$a:ˎ	D
    //   1052: aload_0
    //   1053: getfield 88	com/moat/analytics/mobile/kiip/y:ˊ	Lcom/moat/analytics/mobile/kiip/y$a;
    //   1056: getfield 98	com/moat/analytics/mobile/kiip/y$a:ˎ	D
    //   1059: dcmpl
    //   1060: ifeq +8 -> 1068
    //   1063: goto_w 0 0 0 10
    //   1068: goto_w 0 0 0 44
    //   1073: aload_0
    //   1074: aload_2
    //   1075: putfield 88	com/moat/analytics/mobile/kiip/y:ˊ	Lcom/moat/analytics/mobile/kiip/y$a;
    //   1078: aload_0
    //   1079: new 75	org/json/JSONObject
    //   1082: dup
    //   1083: aload_0
    //   1084: getfield 88	com/moat/analytics/mobile/kiip/y:ˊ	Lcom/moat/analytics/mobile/kiip/y$a;
    //   1087: getfield 96	com/moat/analytics/mobile/kiip/y$a:ˊ	Landroid/graphics/Rect;
    //   1090: aload 6
    //   1092: invokestatic 144	com/moat/analytics/mobile/kiip/y:ˎ	(Landroid/graphics/Rect;Landroid/util/DisplayMetrics;)Landroid/graphics/Rect;
    //   1095: invokestatic 147	com/moat/analytics/mobile/kiip/y:ॱ	(Landroid/graphics/Rect;)Ljava/util/HashMap;
    //   1098: invokespecial 181	org/json/JSONObject:<init>	(Ljava/util/Map;)V
    //   1101: putfield 92	com/moat/analytics/mobile/kiip/y:ˏ	Lorg/json/JSONObject;
    //   1104: iconst_1
    //   1105: istore 5
    //   1107: goto_w 0 0 0 5
    //   1112: aload_3
    //   1113: ldc 7
    //   1115: aload_2
    //   1116: getfield 98	com/moat/analytics/mobile/kiip/y$a:ˎ	D
    //   1119: invokestatic 155	java/lang/Double:valueOf	(D)Ljava/lang/Double;
    //   1122: invokeinterface 195 3 0
    //   1127: pop
    //   1128: aload_0
    //   1129: getfield 87	com/moat/analytics/mobile/kiip/y:ʽ	Lorg/json/JSONObject;
    //   1132: ifnull +8 -> 1140
    //   1135: goto_w 0 0 9 67
    //   1140: goto_w 0 0 9 56
    //   1145: aload_1
    //   1146: aload_0
    //   1147: getfield 94	com/moat/analytics/mobile/kiip/y:ॱ	Landroid/graphics/Rect;
    //   1150: invokevirtual 107	android/graphics/Rect:equals	(Ljava/lang/Object;)Z
    //   1153: ifne +8 -> 1161
    //   1156: goto_w 0 0 0 10
    //   1161: goto_w 0 0 0 38
    //   1166: aload_0
    //   1167: aload_1
    //   1168: putfield 94	com/moat/analytics/mobile/kiip/y:ॱ	Landroid/graphics/Rect;
    //   1171: aload_0
    //   1172: new 75	org/json/JSONObject
    //   1175: dup
    //   1176: aload_1
    //   1177: aload 6
    //   1179: invokestatic 144	com/moat/analytics/mobile/kiip/y:ˎ	(Landroid/graphics/Rect;Landroid/util/DisplayMetrics;)Landroid/graphics/Rect;
    //   1182: invokestatic 147	com/moat/analytics/mobile/kiip/y:ॱ	(Landroid/graphics/Rect;)Ljava/util/HashMap;
    //   1185: invokespecial 181	org/json/JSONObject:<init>	(Ljava/util/Map;)V
    //   1188: putfield 87	com/moat/analytics/mobile/kiip/y:ʽ	Lorg/json/JSONObject;
    //   1191: iconst_1
    //   1192: istore 5
    //   1194: goto_w 0 0 0 5
    //   1199: aload_0
    //   1200: getfield 95	com/moat/analytics/mobile/kiip/y:ᐝ	Lorg/json/JSONObject;
    //   1203: ifnull +8 -> 1211
    //   1206: goto_w 0 0 9 37
    //   1211: goto_w 0 0 9 25
    //   1216: aload 10
    //   1218: aload_0
    //   1219: getfield 90	com/moat/analytics/mobile/kiip/y:ˋ	Landroid/graphics/Rect;
    //   1222: invokevirtual 107	android/graphics/Rect:equals	(Ljava/lang/Object;)Z
    //   1225: ifne +8 -> 1233
    //   1228: goto_w 0 0 0 10
    //   1233: goto_w 0 0 0 40
    //   1238: aload_0
    //   1239: aload 10
    //   1241: putfield 90	com/moat/analytics/mobile/kiip/y:ˋ	Landroid/graphics/Rect;
    //   1244: aload_0
    //   1245: new 75	org/json/JSONObject
    //   1248: dup
    //   1249: aload 10
    //   1251: aload 6
    //   1253: invokestatic 144	com/moat/analytics/mobile/kiip/y:ˎ	(Landroid/graphics/Rect;Landroid/util/DisplayMetrics;)Landroid/graphics/Rect;
    //   1256: invokestatic 147	com/moat/analytics/mobile/kiip/y:ॱ	(Landroid/graphics/Rect;)Ljava/util/HashMap;
    //   1259: invokespecial 181	org/json/JSONObject:<init>	(Ljava/util/Map;)V
    //   1262: putfield 95	com/moat/analytics/mobile/kiip/y:ᐝ	Lorg/json/JSONObject;
    //   1265: iconst_1
    //   1266: istore 5
    //   1268: goto_w 0 0 0 5
    //   1273: aload_0
    //   1274: getfield 86	com/moat/analytics/mobile/kiip/y:ʼ	Ljava/util/HashMap;
    //   1277: ifnull +8 -> 1285
    //   1280: goto_w 0 0 9 3
    //   1285: goto_w 0 0 8 -9
    //   1290: aload_3
    //   1291: aload_0
    //   1292: getfield 86	com/moat/analytics/mobile/kiip/y:ʼ	Ljava/util/HashMap;
    //   1295: invokeinterface 194 2 0
    //   1300: ifne +8 -> 1308
    //   1303: goto_w 0 0 9 20
    //   1308: goto_w 0 0 9 8
    //   1313: aload_0
    //   1314: aload_3
    //   1315: putfield 86	com/moat/analytics/mobile/kiip/y:ʼ	Ljava/util/HashMap;
    //   1318: iconst_1
    //   1319: istore 5
    //   1321: goto_w 0 0 0 5
    //   1326: invokestatic 137	com/moat/analytics/mobile/kiip/k:ˎ	()Lcom/moat/analytics/mobile/kiip/k;
    //   1329: invokevirtual 139	com/moat/analytics/mobile/kiip/k:ॱ	()Landroid/location/Location;
    //   1332: dup
    //   1333: astore_1
    //   1334: aload_0
    //   1335: getfield 85	com/moat/analytics/mobile/kiip/y:ʻ	Landroid/location/Location;
    //   1338: invokestatic 138	com/moat/analytics/mobile/kiip/k:ˎ	(Landroid/location/Location;Landroid/location/Location;)Z
    //   1341: ifne +8 -> 1349
    //   1344: goto_w 0 0 9 19
    //   1349: goto_w 0 0 9 7
    //   1354: iconst_1
    //   1355: istore 5
    //   1357: aload_0
    //   1358: aload_1
    //   1359: putfield 85	com/moat/analytics/mobile/kiip/y:ʻ	Landroid/location/Location;
    //   1362: goto_w 0 0 0 5
    //   1367: iload 5
    //   1369: ifeq +8 -> 1377
    //   1372: goto_w 0 0 9 26
    //   1377: goto_w 0 0 9 15
    //   1382: new 75	org/json/JSONObject
    //   1385: dup
    //   1386: aload_0
    //   1387: getfield 86	com/moat/analytics/mobile/kiip/y:ʼ	Ljava/util/HashMap;
    //   1390: invokespecial 181	org/json/JSONObject:<init>	(Ljava/util/Map;)V
    //   1393: dup
    //   1394: astore_2
    //   1395: ldc 21
    //   1397: aload_0
    //   1398: getfield 87	com/moat/analytics/mobile/kiip/y:ʽ	Lorg/json/JSONObject;
    //   1401: invokevirtual 182	org/json/JSONObject:accumulate	(Ljava/lang/String;Ljava/lang/Object;)Lorg/json/JSONObject;
    //   1404: pop
    //   1405: aload_2
    //   1406: ldc 24
    //   1408: aload_0
    //   1409: getfield 95	com/moat/analytics/mobile/kiip/y:ᐝ	Lorg/json/JSONObject;
    //   1412: invokevirtual 182	org/json/JSONObject:accumulate	(Ljava/lang/String;Ljava/lang/Object;)Lorg/json/JSONObject;
    //   1415: pop
    //   1416: aload_2
    //   1417: ldc 25
    //   1419: aload_0
    //   1420: getfield 92	com/moat/analytics/mobile/kiip/y:ˏ	Lorg/json/JSONObject;
    //   1423: invokevirtual 182	org/json/JSONObject:accumulate	(Ljava/lang/String;Ljava/lang/Object;)Lorg/json/JSONObject;
    //   1426: pop
    //   1427: aload_2
    //   1428: ldc 19
    //   1430: aload_0
    //   1431: getfield 92	com/moat/analytics/mobile/kiip/y:ˏ	Lorg/json/JSONObject;
    //   1434: invokevirtual 182	org/json/JSONObject:accumulate	(Ljava/lang/String;Ljava/lang/Object;)Lorg/json/JSONObject;
    //   1437: pop
    //   1438: aload_2
    //   1439: ldc 26
    //   1441: aload_0
    //   1442: getfield 88	com/moat/analytics/mobile/kiip/y:ˊ	Lcom/moat/analytics/mobile/kiip/y$a;
    //   1445: getfield 97	com/moat/analytics/mobile/kiip/y$a:ˋ	D
    //   1448: invokestatic 155	java/lang/Double:valueOf	(D)Ljava/lang/Double;
    //   1451: invokevirtual 182	org/json/JSONObject:accumulate	(Ljava/lang/String;Ljava/lang/Object;)Lorg/json/JSONObject;
    //   1454: pop
    //   1455: aload_1
    //   1456: ifnull +8 -> 1464
    //   1459: goto_w 0 0 8 -20
    //   1464: goto_w 0 0 8 -32
    //   1469: aload_2
    //   1470: ldc 17
    //   1472: aload_1
    //   1473: dup
    //   1474: astore 13
    //   1476: ifnonnull +8 -> 1484
    //   1479: goto_w 0 0 9 0
    //   1484: goto_w 0 0 8 -12
    //   1489: aconst_null
    //   1490: goto_w 0 0 0 92
    //   1495: new 69	java/util/HashMap
    //   1498: dup
    //   1499: invokespecial 179	java/util/HashMap:<init>	()V
    //   1502: dup
    //   1503: astore 7
    //   1505: ldc 16
    //   1507: aload 13
    //   1509: invokevirtual 115	android/location/Location:getLatitude	()D
    //   1512: invokestatic 154	java/lang/Double:toString	(D)Ljava/lang/String;
    //   1515: invokeinterface 195 3 0
    //   1520: pop
    //   1521: aload 7
    //   1523: ldc 18
    //   1525: aload 13
    //   1527: invokevirtual 116	android/location/Location:getLongitude	()D
    //   1530: invokestatic 154	java/lang/Double:toString	(D)Ljava/lang/String;
    //   1533: invokeinterface 195 3 0
    //   1538: pop
    //   1539: aload 7
    //   1541: ldc 23
    //   1543: aload 13
    //   1545: invokevirtual 117	android/location/Location:getTime	()J
    //   1548: invokestatic 161	java/lang/Long:toString	(J)Ljava/lang/String;
    //   1551: invokeinterface 195 3 0
    //   1556: pop
    //   1557: aload 7
    //   1559: ldc 12
    //   1561: aload 13
    //   1563: invokevirtual 114	android/location/Location:getAccuracy	()F
    //   1566: invokestatic 156	java/lang/Float:toString	(F)Ljava/lang/String;
    //   1569: invokeinterface 195 3 0
    //   1574: pop
    //   1575: aload 7
    //   1577: goto_w 0 0 0 5
    //   1582: dup
    //   1583: astore 12
    //   1585: ifnonnull +8 -> 1593
    //   1588: goto_w 0 0 8 -74
    //   1593: goto_w 0 0 8 -85
    //   1598: aconst_null
    //   1599: goto_w 0 0 0 19
    //   1604: new 75	org/json/JSONObject
    //   1607: dup
    //   1608: aload 12
    //   1610: invokespecial 181	org/json/JSONObject:<init>	(Ljava/util/Map;)V
    //   1613: goto_w 0 0 0 5
    //   1618: invokevirtual 182	org/json/JSONObject:accumulate	(Ljava/lang/String;Ljava/lang/Object;)Lorg/json/JSONObject;
    //   1621: pop
    //   1622: goto_w 0 0 0 5
    //   1627: aload_2
    //   1628: invokevirtual 183	org/json/JSONObject:toString	()Ljava/lang/String;
    //   1631: astore 4
    //   1633: aload_0
    //   1634: aload 4
    //   1636: putfield 91	com/moat/analytics/mobile/kiip/y:ˎ	Ljava/lang/String;
    //   1639: goto_w 0 0 0 5
    //   1644: return
    //   1645: invokestatic 140	com/moat/analytics/mobile/kiip/o:ॱ	(Ljava/lang/Exception;)V
    //   1648: aload_0
    //   1649: aload 4
    //   1651: putfield 91	com/moat/analytics/mobile/kiip/y:ˎ	Ljava/lang/String;
    //   1654: return
    //   1655: getstatic 93	com/moat/analytics/mobile/kiip/y:ˏॱ	I
    //   1658: bipush 63
    //   1660: iadd
    //   1661: dup
    //   1662: sipush 128
    //   1665: irem
    //   1666: putstatic 89	com/moat/analytics/mobile/kiip/y:ˊॱ	I
    //   1669: iconst_2
    //   1670: irem
    //   1671: ifeq +8 -> 1679
    //   1674: goto_w 0 0 0 10
    //   1679: goto_w -1 -1 -7 -72
    //   1684: goto_w -1 -1 -7 -77
    //   1689: getstatic 89	com/moat/analytics/mobile/kiip/y:ˊॱ	I
    //   1692: bipush 63
    //   1694: iadd
    //   1695: dup
    //   1696: sipush 128
    //   1699: irem
    //   1700: putstatic 93	com/moat/analytics/mobile/kiip/y:ˏॱ	I
    //   1703: iconst_2
    //   1704: irem
    //   1705: ifne +8 -> 1713
    //   1708: goto_w 0 0 8 103
    //   1713: goto_w 0 0 8 91
    //   1718: new 40	android/util/DisplayMetrics
    //   1721: dup
    //   1722: invokespecial 118	android/util/DisplayMetrics:<init>	()V
    //   1725: astore 13
    //   1727: aload 12
    //   1729: invokevirtual 102	android/app/Activity:getWindowManager	()Landroid/view/WindowManager;
    //   1732: invokeinterface 184 1 0
    //   1737: aload 13
    //   1739: invokevirtual 119	android/view/Display:getRealMetrics	(Landroid/util/DisplayMetrics;)V
    //   1742: aload 13
    //   1744: goto_w -1 -1 -7 -65
    //   1749: getstatic 89	com/moat/analytics/mobile/kiip/y:ˊॱ	I
    //   1752: bipush 121
    //   1754: iadd
    //   1755: dup
    //   1756: sipush 128
    //   1759: irem
    //   1760: putstatic 93	com/moat/analytics/mobile/kiip/y:ˏॱ	I
    //   1763: iconst_2
    //   1764: irem
    //   1765: ifne +8 -> 1773
    //   1768: goto_w 0 0 8 78
    //   1773: goto_w 0 0 8 67
    //   1778: iconst_1
    //   1779: goto_w -1 -1 -6 13
    //   1784: getstatic 89	com/moat/analytics/mobile/kiip/y:ˊॱ	I
    //   1787: bipush 27
    //   1789: iadd
    //   1790: dup
    //   1791: sipush 128
    //   1794: irem
    //   1795: putstatic 93	com/moat/analytics/mobile/kiip/y:ˏॱ	I
    //   1798: iconst_2
    //   1799: irem
    //   1800: ifne +8 -> 1808
    //   1803: goto_w 0 0 0 10
    //   1808: goto_w -1 -1 -6 101
    //   1813: goto_w -1 -1 -6 96
    //   1818: getstatic 89	com/moat/analytics/mobile/kiip/y:ˊॱ	I
    //   1821: bipush 33
    //   1823: iadd
    //   1824: dup
    //   1825: sipush 128
    //   1828: irem
    //   1829: putstatic 93	com/moat/analytics/mobile/kiip/y:ˏॱ	I
    //   1832: iconst_2
    //   1833: irem
    //   1834: ifne +8 -> 1842
    //   1837: goto_w 0 0 0 10
    //   1842: goto_w -1 -1 -6 -111
    //   1847: goto_w -1 -1 -6 -116
    //   1852: getstatic 89	com/moat/analytics/mobile/kiip/y:ˊॱ	I
    //   1855: bipush 55
    //   1857: iadd
    //   1858: dup
    //   1859: sipush 128
    //   1862: irem
    //   1863: putstatic 93	com/moat/analytics/mobile/kiip/y:ˏॱ	I
    //   1866: iconst_2
    //   1867: irem
    //   1868: ifne +8 -> 1876
    //   1871: goto_w 0 0 8 11
    //   1876: goto_w 0 0 8 0
    //   1881: iconst_1
    //   1882: goto_w -1 -1 -6 -61
    //   1887: getstatic 93	com/moat/analytics/mobile/kiip/y:ˏॱ	I
    //   1890: bipush 99
    //   1892: iadd
    //   1893: dup
    //   1894: sipush 128
    //   1897: irem
    //   1898: putstatic 89	com/moat/analytics/mobile/kiip/y:ˊॱ	I
    //   1901: iconst_2
    //   1902: irem
    //   1903: ifeq +8 -> 1911
    //   1906: goto_w 0 0 8 17
    //   1911: goto_w 0 0 8 5
    //   1916: iload 13
    //   1918: ifeq +8 -> 1926
    //   1921: goto_w 0 0 8 42
    //   1926: goto_w 0 0 8 30
    //   1931: getstatic 89	com/moat/analytics/mobile/kiip/y:ˊॱ	I
    //   1934: bipush 35
    //   1936: iadd
    //   1937: dup
    //   1938: sipush 128
    //   1941: irem
    //   1942: putstatic 93	com/moat/analytics/mobile/kiip/y:ˏॱ	I
    //   1945: iconst_2
    //   1946: irem
    //   1947: ifne +8 -> 1955
    //   1950: goto_w 0 0 8 48
    //   1955: goto_w 0 0 8 37
    //   1960: iload 9
    //   1962: ifle +8 -> 1970
    //   1965: goto_w 0 0 8 74
    //   1970: goto_w 0 0 8 62
    //   1975: getstatic 93	com/moat/analytics/mobile/kiip/y:ˏॱ	I
    //   1978: bipush 65
    //   1980: iadd
    //   1981: dup
    //   1982: sipush 128
    //   1985: irem
    //   1986: putstatic 89	com/moat/analytics/mobile/kiip/y:ˊॱ	I
    //   1989: iconst_2
    //   1990: irem
    //   1991: ifeq +8 -> 1999
    //   1994: goto_w 0 0 0 10
    //   1999: goto_w -1 -1 -5 69
    //   2004: goto_w -1 -1 -5 64
    //   2009: getstatic 93	com/moat/analytics/mobile/kiip/y:ˏॱ	I
    //   2012: bipush 9
    //   2014: iadd
    //   2015: dup
    //   2016: sipush 128
    //   2019: irem
    //   2020: putstatic 89	com/moat/analytics/mobile/kiip/y:ˊॱ	I
    //   2023: iconst_2
    //   2024: irem
    //   2025: ifeq +8 -> 2033
    //   2028: goto_w 0 0 0 10
    //   2033: goto_w -1 -1 -5 -70
    //   2038: goto_w -1 -1 -5 -75
    //   2043: getstatic 89	com/moat/analytics/mobile/kiip/y:ˊॱ	I
    //   2046: bipush 73
    //   2048: iadd
    //   2049: dup
    //   2050: sipush 128
    //   2053: irem
    //   2054: putstatic 93	com/moat/analytics/mobile/kiip/y:ˏॱ	I
    //   2057: iconst_2
    //   2058: irem
    //   2059: ifne +8 -> 2067
    //   2062: goto_w 0 0 0 10
    //   2067: goto_w -1 -1 -5 -22
    //   2072: goto_w -1 -1 -5 -27
    //   2077: getstatic 93	com/moat/analytics/mobile/kiip/y:ˏॱ	I
    //   2080: bipush 71
    //   2082: iadd
    //   2083: dup
    //   2084: sipush 128
    //   2087: irem
    //   2088: putstatic 89	com/moat/analytics/mobile/kiip/y:ˊॱ	I
    //   2091: iconst_2
    //   2092: irem
    //   2093: ifeq +8 -> 2101
    //   2096: goto_w 0 0 0 10
    //   2101: goto_w -1 -1 -4 68
    //   2106: goto_w -1 -1 -4 63
    //   2111: getstatic 93	com/moat/analytics/mobile/kiip/y:ˏॱ	I
    //   2114: bipush 97
    //   2116: iadd
    //   2117: dup
    //   2118: sipush 128
    //   2121: irem
    //   2122: putstatic 89	com/moat/analytics/mobile/kiip/y:ˊॱ	I
    //   2125: iconst_2
    //   2126: irem
    //   2127: ifeq +8 -> 2135
    //   2130: goto_w 0 0 0 10
    //   2135: goto_w -1 -1 -4 105
    //   2140: goto_w -1 -1 -4 100
    //   2145: getstatic 89	com/moat/analytics/mobile/kiip/y:ˊॱ	I
    //   2148: bipush 51
    //   2150: iadd
    //   2151: dup
    //   2152: sipush 128
    //   2155: irem
    //   2156: putstatic 93	com/moat/analytics/mobile/kiip/y:ˏॱ	I
    //   2159: iconst_2
    //   2160: irem
    //   2161: ifne +8 -> 2169
    //   2164: goto_w 0 0 7 -90
    //   2169: goto_w 0 0 7 -101
    //   2174: iconst_1
    //   2175: istore 5
    //   2177: aload_0
    //   2178: aload_1
    //   2179: putfield 85	com/moat/analytics/mobile/kiip/y:ʻ	Landroid/location/Location;
    //   2182: goto_w -1 -1 -4 -47
    //   2187: getstatic 89	com/moat/analytics/mobile/kiip/y:ˊॱ	I
    //   2190: bipush 31
    //   2192: iadd
    //   2193: dup
    //   2194: sipush 128
    //   2197: irem
    //   2198: putstatic 93	com/moat/analytics/mobile/kiip/y:ˏॱ	I
    //   2201: iconst_2
    //   2202: irem
    //   2203: ifne +8 -> 2211
    //   2206: goto_w 0 0 0 10
    //   2211: goto_w -1 -1 -3 26
    //   2216: goto_w -1 -1 -3 21
    //   2221: getstatic 89	com/moat/analytics/mobile/kiip/y:ˊॱ	I
    //   2224: bipush 123
    //   2226: iadd
    //   2227: dup
    //   2228: sipush 128
    //   2231: irem
    //   2232: putstatic 93	com/moat/analytics/mobile/kiip/y:ˏॱ	I
    //   2235: iconst_2
    //   2236: irem
    //   2237: ifne +8 -> 2245
    //   2240: goto_w 0 0 0 10
    //   2245: goto_w -1 -1 -3 121
    //   2250: goto_w -1 -1 -3 116
    //   2255: lookupswitch	default:+-611->1644, 33:+-2221->34, 86:+-611->1644
    //   2280: bipush 86
    //   2282: goto_w -1 -1 -1 -27
    //   2287: bipush 33
    //   2289: goto_w -1 -1 -1 -34
    //   2294: tableswitch	default:+-2167->127, 0:+-2167->127, 1:+-2239->55
    //   2316: iconst_0
    //   2317: goto_w -1 -1 -1 -23
    //   2322: iconst_1
    //   2323: goto_w -1 -1 -1 -29
    //   2328: lookupswitch	default:+-673->1655, 13:+-2201->127, 99:+-673->1655
    //   2356: bipush 13
    //   2358: goto_w -1 -1 -1 -30
    //   2363: bipush 99
    //   2365: goto_w -1 -1 -1 -37
    //   2370: lookupswitch	default:+-2243->127, 53:+-681->1689, 83:+-2243->127
    //   2396: bipush 83
    //   2398: goto_w -1 -1 -1 -28
    //   2403: bipush 53
    //   2405: goto_w -1 -1 -1 -35
    //   2410: lookupswitch	default:+-2244->166, 31:+-2199->211, 71:+-2244->166
    //   2436: bipush 31
    //   2438: goto_w -1 -1 -1 -28
    //   2443: bipush 71
    //   2445: goto_w -1 -1 -1 -35
    //   2450: lookupswitch	default:+-2245->205, 67:+-2245->205, 99:+-2269->181
    //   2476: bipush 67
    //   2478: goto_w -1 -1 -1 -28
    //   2483: bipush 99
    //   2485: goto_w -1 -1 -1 -35
    //   2490: tableswitch	default:+-2285->205, 0:+-2285->205, 1:+-741->1749
    //   2512: iconst_0
    //   2513: goto_w -1 -1 -1 -23
    //   2518: iconst_1
    //   2519: goto_w -1 -1 -1 -29
    //   2524: lookupswitch	default:+-2298->226, 23:+-2298->226, 87:+-2274->250
    //   2552: bipush 87
    //   2554: goto_w -1 -1 -1 -30
    //   2559: bipush 23
    //   2561: goto_w -1 -1 -1 -37
    //   2566: lookupswitch	default:+-2316->250, 62:+-2316->250, 71:+-2322->244
    //   2592: bipush 62
    //   2594: goto_w -1 -1 -1 -28
    //   2599: bipush 71
    //   2601: goto_w -1 -1 -1 -35
    //   2606: lookupswitch	default:+-2331->275, 31:+-2331->275, 71:+-2307->299
    //   2632: bipush 71
    //   2634: goto_w -1 -1 -1 -28
    //   2639: bipush 31
    //   2641: goto_w -1 -1 -1 -35
    //   2646: lookupswitch	default:+-2353->293, 27:+-2347->299, 51:+-2353->293
    //   2672: bipush 27
    //   2674: goto_w -1 -1 -1 -28
    //   2679: bipush 51
    //   2681: goto_w -1 -1 -1 -35
    //   2686: lookupswitch	default:+-2362->324, 10:+-2362->324, 14:+-2344->342
    //   2712: bipush 14
    //   2714: goto_w -1 -1 -1 -28
    //   2719: bipush 10
    //   2721: goto_w -1 -1 -1 -35
    //   2726: lookupswitch	default:+-2378->348, 6:+-2378->348, 68:+-2384->342
    //   2752: bipush 6
    //   2754: goto_w -1 -1 -1 -28
    //   2759: bipush 68
    //   2761: goto_w -1 -1 -1 -35
    //   2766: lookupswitch	default:+-982->1784, 15:+-982->1784, 23:+-2387->379
    //   2792: bipush 23
    //   2794: goto_w -1 -1 -1 -28
    //   2799: bipush 15
    //   2801: goto_w -1 -1 -1 -35
    //   2806: tableswitch	default:+-988->1818, 0:+-2349->457, 1:+-988->1818
    //   2828: iconst_0
    //   2829: goto_w -1 -1 -1 -23
    //   2834: iconst_1
    //   2835: goto_w -1 -1 -1 -29
    //   2840: tableswitch	default:+-2350->490, 0:+-2344->496, 1:+-2350->490
    //   2864: iconst_0
    //   2865: goto_w -1 -1 -1 -25
    //   2870: iconst_1
    //   2871: goto_w -1 -1 -1 -31
    //   2876: lookupswitch	default:+-2341->535, 48:+-1024->1852, 79:+-2341->535
    //   2904: bipush 79
    //   2906: goto_w -1 -1 -1 -30
    //   2911: bipush 48
    //   2913: goto_w -1 -1 -1 -37
    //   2918: tableswitch	default:+-2306->612, 0:+-2296->622, 1:+-2306->612
    //   2940: iconst_0
    //   2941: goto_w -1 -1 -1 -23
    //   2946: iconst_1
    //   2947: goto_w -1 -1 -1 -29
    //   2952: lookupswitch	default:+-1976->976, 45:+-1065->1887, 53:+-1976->976
    //   2980: bipush 53
    //   2982: goto_w -1 -1 -1 -30
    //   2987: bipush 45
    //   2989: goto_w -1 -1 -1 -37
    //   2994: lookupswitch	default:+-2018->976, 44:+-2281->713, 48:+-2018->976
    //   3020: bipush 48
    //   3022: goto_w -1 -1 -1 -28
    //   3027: bipush 44
    //   3029: goto_w -1 -1 -1 -35
    //   3034: tableswitch	default:+-2058->976, 0:+-2306->728, 1:+-2058->976
    //   3056: iconst_1
    //   3057: goto_w -1 -1 -1 -23
    //   3062: iconst_0
    //   3063: goto_w -1 -1 -1 -29
    //   3068: lookupswitch	default:+-1137->1931, 23:+-1137->1931, 34:+-2092->976
    //   3096: bipush 34
    //   3098: goto_w -1 -1 -1 -30
    //   3103: bipush 23
    //   3105: goto_w -1 -1 -1 -37
    //   3110: tableswitch	default:+-2353->757, 0:+-2353->757, 1:+-2134->976
    //   3132: iconst_1
    //   3133: goto_w -1 -1 -1 -23
    //   3138: iconst_0
    //   3139: goto_w -1 -1 -1 -29
    //   3144: tableswitch	default:+-2168->976, 0:+-2168->976, 1:+-1169->1975
    //   3168: iconst_0
    //   3169: goto_w -1 -1 -1 -25
    //   3174: iconst_1
    //   3175: goto_w -1 -1 -1 -31
    //   3180: tableswitch	default:+-2348->832, 0:+-2348->832, 1:+-2361->819
    //   3204: iconst_0
    //   3205: goto_w -1 -1 -1 -25
    //   3210: iconst_1
    //   3211: goto_w -1 -1 -1 -31
    //   3216: tableswitch	default:+-2240->976, 0:+-2240->976, 1:+-2354->862
    //   3240: iconst_0
    //   3241: goto_w -1 -1 -1 -25
    //   3246: iconst_1
    //   3247: goto_w -1 -1 -1 -31
    //   3252: lookupswitch	default:+-2349->903, 36:+-2349->903, 70:+-2360->892
    //   3280: bipush 36
    //   3282: goto_w -1 -1 -1 -30
    //   3287: bipush 70
    //   3289: goto_w -1 -1 -1 -37
    //   3294: tableswitch	default:+-2376->918, 0:+-2376->918, 1:+-2318->976
    //   3316: iconst_1
    //   3317: goto_w -1 -1 -1 -23
    //   3322: iconst_0
    //   3323: goto_w -1 -1 -1 -29
    //   3328: tableswitch	default:+-2373->955, 0:+-2373->955, 1:+-1319->2009
    //   3352: iconst_0
    //   3353: goto_w -1 -1 -1 -25
    //   3358: iconst_1
    //   3359: goto_w -1 -1 -1 -31
    //   3364: tableswitch	default:+-2368->996, 0:+-2291->1073, 1:+-2368->996
    //   3388: iconst_0
    //   3389: goto_w -1 -1 -1 -25
    //   3394: iconst_1
    //   3395: goto_w -1 -1 -1 -31
    //   3400: lookupswitch	default:+-1357->2043, 18:+-2327->1073, 75:+-1357->2043
    //   3428: bipush 18
    //   3430: goto_w -1 -1 -1 -30
    //   3435: bipush 75
    //   3437: goto_w -1 -1 -1 -37
    //   3442: tableswitch	default:+-2394->1048, 0:+-2369->1073, 1:+-2394->1048
    //   3464: iconst_0
    //   3465: goto_w -1 -1 -1 -23
    //   3470: iconst_1
    //   3471: goto_w -1 -1 -1 -29
    //   3476: tableswitch	default:+-2310->1166, 0:+-1399->2077, 1:+-2310->1166
    //   3500: iconst_1
    //   3501: goto_w -1 -1 -1 -25
    //   3506: iconst_0
    //   3507: goto_w -1 -1 -1 -31
    //   3512: lookupswitch	default:+-2274->1238, 52:+-2274->1238, 83:+-1401->2111
    //   3540: bipush 52
    //   3542: goto_w -1 -1 -1 -30
    //   3547: bipush 83
    //   3549: goto_w -1 -1 -1 -37
    //   3554: lookupswitch	default:+-2241->1313, 1:+-2264->1290, 50:+-2241->1313
    //   3580: bipush 50
    //   3582: goto_w -1 -1 -1 -28
    //   3587: bipush 1
    //   3589: goto_w -1 -1 -1 -35
    //   3594: lookupswitch	default:+-2268->1326, 74:+-2281->1313, 98:+-2268->1326
    //   3620: bipush 98
    //   3622: goto_w -1 -1 -1 -28
    //   3627: bipush 74
    //   3629: goto_w -1 -1 -1 -35
    //   3634: lookupswitch	default:+-2267->1367, 40:+-2267->1367, 75:+-1489->2145
    //   3660: bipush 40
    //   3662: goto_w -1 -1 -1 -28
    //   3667: bipush 75
    //   3669: goto_w -1 -1 -1 -35
    //   3674: tableswitch	default:+-2292->1382, 0:+-2030->1644, 1:+-2292->1382
    //   3696: iconst_0
    //   3697: goto_w -1 -1 -1 -23
    //   3702: iconst_1
    //   3703: goto_w -1 -1 -1 -29
    //   3708: lookupswitch	default:+-1521->2187, 21:+-2081->1627, 45:+-1521->2187
    //   3736: bipush 21
    //   3738: goto_w -1 -1 -1 -30
    //   3743: bipush 45
    //   3745: goto_w -1 -1 -1 -37
    //   3750: lookupswitch	default:+-2261->1489, 53:+-2255->1495, 87:+-2261->1489
    //   3776: bipush 53
    //   3778: goto_w -1 -1 -1 -28
    //   3783: bipush 87
    //   3785: goto_w -1 -1 -1 -35
    //   3790: tableswitch	default:+-2186->1604, 0:+-1569->2221, 1:+-2186->1604
    //   3812: iconst_1
    //   3813: goto_w -1 -1 -1 -23
    //   3818: iconst_0
    //   3819: goto_w -1 -1 -1 -29
    //   3824: lookupswitch	default:+-2106->1718, 89:+-3728->96, 97:+-2106->1718
    //   3852: bipush 89
    //   3854: goto_w -1 -1 -1 -30
    //   3859: bipush 97
    //   3861: goto_w -1 -1 -1 -37
    //   3866: tableswitch	default:+-3667->199, 0:+-2088->1778, 1:+-3667->199
    //   3888: iconst_1
    //   3889: goto_w -1 -1 -1 -23
    //   3894: iconst_0
    //   3895: goto_w -1 -1 -1 -29
    //   3900: tableswitch	default:+-3371->529, 0:+-2019->1881, 1:+-3371->529
    //   3924: iconst_1
    //   3925: goto_w -1 -1 -1 -25
    //   3930: iconst_0
    //   3931: goto_w -1 -1 -1 -31
    //   3936: lookupswitch	default:+-2020->1916, 22:+-3238->698, 60:+-2020->1916
    //   3964: bipush 22
    //   3966: goto_w -1 -1 -1 -30
    //   3971: bipush 60
    //   3973: goto_w -1 -1 -1 -37
    //   3978: lookupswitch	default:+-3265->713, 58:+-3265->713, 91:+-3002->976
    //   4004: bipush 91
    //   4006: goto_w -1 -1 -1 -28
    //   4011: bipush 58
    //   4013: goto_w -1 -1 -1 -35
    //   4018: tableswitch	default:+-2058->1960, 0:+-2058->1960, 1:+-3276->742
    //   4040: iconst_1
    //   4041: goto_w -1 -1 -1 -23
    //   4046: iconst_0
    //   4047: goto_w -1 -1 -1 -29
    //   4052: lookupswitch	default:+-3076->976, 11:+-3076->976, 76:+-3295->757
    //   4080: bipush 11
    //   4082: goto_w -1 -1 -1 -30
    //   4087: bipush 76
    //   4089: goto_w -1 -1 -1 -37
    //   4094: tableswitch	default:+-2740->1354, 0:+-2740->1354, 1:+-1920->2174
    //   4116: iconst_0
    //   4117: goto_w -1 -1 -1 -23
    //   4122: iconst_1
    //   4123: goto_w -1 -1 -1 -29
    // Line number table:
    //   Java source line #114	-> byte code offset #5
    //   Java source line #115	-> byte code offset #13
    //   Java source line #116	-> byte code offset #17
    //   Java source line #118	-> byte code offset #20
    //   Java source line #119	-> byte code offset #34
    //   Java source line #1524	-> byte code offset #37
    //   Java source line #1525	-> byte code offset #55
    //   Java source line #1526	-> byte code offset #71
    //   Java source line #1527	-> byte code offset #81
    //   Java source line #1528	-> byte code offset #96
    //   Java source line #1529	-> byte code offset #105
    //   Java source line #1530	-> byte code offset #120
    //   Java source line #1534	-> byte code offset #127
    //   Java source line #1535	-> byte code offset #132
    //   Java source line #1536	-> byte code offset #135
    //   Java source line #119	-> byte code offset #143
    //   Java source line #120	-> byte code offset #145
    //   Java source line #2190	-> byte code offset #148
    //   Java source line #2191	-> byte code offset #166
    //   Java source line #2194	-> byte code offset #211
    //   Java source line #120	-> byte code offset #256
    //   Java source line #121	-> byte code offset #258
    //   Java source line #2199	-> byte code offset #260
    //   Java source line #121	-> byte code offset #305
    //   Java source line #122	-> byte code offset #307
    //   Java source line #2203	-> byte code offset #309
    //   Java source line #122	-> byte code offset #354
    //   Java source line #123	-> byte code offset #356
    //   Java source line #2207	-> byte code offset #358
    //   Java source line #123	-> byte code offset #389
    //   Java source line #124	-> byte code offset #391
    //   Java source line #125	-> byte code offset #408
    //   Java source line #126	-> byte code offset #423
    //   Java source line #127	-> byte code offset #433
    //   Java source line #128	-> byte code offset #472
    //   Java source line #129	-> byte code offset #511
    //   Java source line #130	-> byte code offset #550
    //   Java source line #132	-> byte code offset #564
    //   Java source line #2226	-> byte code offset #567
    //   Java source line #2227	-> byte code offset #574
    //   Java source line #2228	-> byte code offset #581
    //   Java source line #132	-> byte code offset #594
    //   Java source line #133	-> byte code offset #595
    //   Java source line #2232	-> byte code offset #597
    //   Java source line #133	-> byte code offset #638
    //   Java source line #134	-> byte code offset #640
    //   Java source line #2236	-> byte code offset #658
    //   Java source line #2237	-> byte code offset #667
    //   Java source line #2507	-> byte code offset #670
    //   Java source line #2237	-> byte code offset #681
    //   Java source line #2239	-> byte code offset #683
    //   Java source line #2240	-> byte code offset #757
    //   Java source line #2243	-> byte code offset #769
    //   Java source line #2244	-> byte code offset #788
    //   Java source line #3507	-> byte code offset #790
    //   Java source line #2244	-> byte code offset #801
    //   Java source line #2245	-> byte code offset #802
    //   Java source line #2246	-> byte code offset #819
    //   Java source line #2248	-> byte code offset #832
    //   Java source line #2249	-> byte code offset #841
    //   Java source line #2250	-> byte code offset #846
    //   Java source line #2251	-> byte code offset #862
    //   Java source line #2252	-> byte code offset #868
    //   Java source line #2253	-> byte code offset #877
    //   Java source line #2254	-> byte code offset #892
    //   Java source line #2256	-> byte code offset #903
    //   Java source line #2257	-> byte code offset #918
    //   Java source line #2258	-> byte code offset #925
    //   Java source line #2259	-> byte code offset #939
    //   Java source line #2261	-> byte code offset #955
    //   Java source line #2262	-> byte code offset #960
    //   Java source line #2267	-> byte code offset #976
    //   Java source line #134	-> byte code offset #978
    //   Java source line #135	-> byte code offset #979
    //   Java source line #137	-> byte code offset #1032
    //   Java source line #139	-> byte code offset #1073
    //   Java source line #140	-> byte code offset #1078
    //   Java source line #4457	-> byte code offset #1092
    //   Java source line #140	-> byte code offset #1098
    //   Java source line #141	-> byte code offset #1104
    //   Java source line #143	-> byte code offset #1112
    //   Java source line #144	-> byte code offset #1128
    //   Java source line #145	-> byte code offset #1166
    //   Java source line #146	-> byte code offset #1171
    //   Java source line #5457	-> byte code offset #1179
    //   Java source line #146	-> byte code offset #1185
    //   Java source line #147	-> byte code offset #1191
    //   Java source line #149	-> byte code offset #1199
    //   Java source line #150	-> byte code offset #1238
    //   Java source line #151	-> byte code offset #1244
    //   Java source line #6457	-> byte code offset #1253
    //   Java source line #151	-> byte code offset #1259
    //   Java source line #152	-> byte code offset #1265
    //   Java source line #154	-> byte code offset #1273
    //   Java source line #155	-> byte code offset #1313
    //   Java source line #156	-> byte code offset #1318
    //   Java source line #159	-> byte code offset #1326
    //   Java source line #160	-> byte code offset #1333
    //   Java source line #161	-> byte code offset #1354
    //   Java source line #162	-> byte code offset #1357
    //   Java source line #165	-> byte code offset #1367
    //   Java source line #166	-> byte code offset #1382
    //   Java source line #167	-> byte code offset #1394
    //   Java source line #168	-> byte code offset #1405
    //   Java source line #169	-> byte code offset #1416
    //   Java source line #170	-> byte code offset #1427
    //   Java source line #171	-> byte code offset #1438
    //   Java source line #172	-> byte code offset #1455
    //   Java source line #173	-> byte code offset #1469
    //   Java source line #6485	-> byte code offset #1473
    //   Java source line #6493	-> byte code offset #1474
    //   Java source line #6494	-> byte code offset #1489
    //   Java source line #6496	-> byte code offset #1495
    //   Java source line #6497	-> byte code offset #1503
    //   Java source line #6498	-> byte code offset #1521
    //   Java source line #6499	-> byte code offset #1539
    //   Java source line #6500	-> byte code offset #1557
    //   Java source line #6501	-> byte code offset #1575
    //   Java source line #6485	-> byte code offset #1582
    //   Java source line #6486	-> byte code offset #1583
    //   Java source line #6487	-> byte code offset #1598
    //   Java source line #6489	-> byte code offset #1604
    //   Java source line #173	-> byte code offset #1618
    //   Java source line #175	-> byte code offset #1627
    //   Java source line #176	-> byte code offset #1633
    //   Java source line #183	-> byte code offset #1645
    //   Java source line #184	-> byte code offset #1648
    //   Java source line #1528	-> byte code offset #1718
    //   Java source line #1529	-> byte code offset #1727
    //   Java source line #1530	-> byte code offset #1742
    //   Java source line #161	-> byte code offset #2174
    //   Java source line #162	-> byte code offset #2177
    // Exception table:
    //   from	to	target	type
    //   20	34	1645	java/lang/Exception
    //   34	55	1645	java/lang/Exception
    //   55	71	1645	java/lang/Exception
    //   71	96	1645	java/lang/Exception
    //   96	127	1645	java/lang/Exception
    //   127	143	1645	java/lang/Exception
    //   143	166	1645	java/lang/Exception
    //   166	181	1645	java/lang/Exception
    //   181	199	1645	java/lang/Exception
    //   199	205	1645	java/lang/Exception
    //   205	211	1645	java/lang/Exception
    //   211	226	1645	java/lang/Exception
    //   226	244	1645	java/lang/Exception
    //   244	250	1645	java/lang/Exception
    //   250	256	1645	java/lang/Exception
    //   256	275	1645	java/lang/Exception
    //   275	293	1645	java/lang/Exception
    //   293	299	1645	java/lang/Exception
    //   299	305	1645	java/lang/Exception
    //   305	324	1645	java/lang/Exception
    //   324	342	1645	java/lang/Exception
    //   342	348	1645	java/lang/Exception
    //   348	354	1645	java/lang/Exception
    //   354	373	1645	java/lang/Exception
    //   373	379	1645	java/lang/Exception
    //   379	389	1645	java/lang/Exception
    //   389	451	1645	java/lang/Exception
    //   451	457	1645	java/lang/Exception
    //   457	463	1645	java/lang/Exception
    //   463	490	1645	java/lang/Exception
    //   490	496	1645	java/lang/Exception
    //   496	502	1645	java/lang/Exception
    //   502	529	1645	java/lang/Exception
    //   529	535	1645	java/lang/Exception
    //   535	541	1645	java/lang/Exception
    //   541	612	1645	java/lang/Exception
    //   612	622	1645	java/lang/Exception
    //   622	638	1645	java/lang/Exception
    //   638	698	1645	java/lang/Exception
    //   698	713	1645	java/lang/Exception
    //   713	728	1645	java/lang/Exception
    //   728	742	1645	java/lang/Exception
    //   742	757	1645	java/lang/Exception
    //   757	788	1645	java/lang/Exception
    //   788	819	1645	java/lang/Exception
    //   819	832	1645	java/lang/Exception
    //   832	862	1645	java/lang/Exception
    //   862	892	1645	java/lang/Exception
    //   892	903	1645	java/lang/Exception
    //   903	918	1645	java/lang/Exception
    //   918	939	1645	java/lang/Exception
    //   939	955	1645	java/lang/Exception
    //   955	976	1645	java/lang/Exception
    //   976	996	1645	java/lang/Exception
    //   996	1021	1645	java/lang/Exception
    //   1021	1048	1645	java/lang/Exception
    //   1048	1073	1645	java/lang/Exception
    //   1073	1112	1645	java/lang/Exception
    //   1112	1145	1645	java/lang/Exception
    //   1145	1166	1645	java/lang/Exception
    //   1166	1199	1645	java/lang/Exception
    //   1199	1216	1645	java/lang/Exception
    //   1216	1238	1645	java/lang/Exception
    //   1238	1273	1645	java/lang/Exception
    //   1273	1290	1645	java/lang/Exception
    //   1290	1313	1645	java/lang/Exception
    //   1313	1326	1645	java/lang/Exception
    //   1326	1354	1645	java/lang/Exception
    //   1354	1367	1645	java/lang/Exception
    //   1367	1382	1645	java/lang/Exception
    //   1382	1469	1645	java/lang/Exception
    //   1469	1489	1645	java/lang/Exception
    //   1489	1495	1645	java/lang/Exception
    //   1495	1582	1645	java/lang/Exception
    //   1582	1598	1645	java/lang/Exception
    //   1598	1604	1645	java/lang/Exception
    //   1604	1618	1645	java/lang/Exception
    //   1618	1627	1645	java/lang/Exception
    //   1627	1644	1645	java/lang/Exception
    //   1718	1749	1645	java/lang/Exception
    //   1778	1784	1645	java/lang/Exception
    //   1881	1887	1645	java/lang/Exception
    //   1916	1931	1645	java/lang/Exception
    //   1960	1975	1645	java/lang/Exception
    //   2174	2187	1645	java/lang/Exception
  }
  
  /* Error */
  private static float ˊ(View arg0)
  {
    // Byte code:
    //   0: goto_w 0 0 0 5
    //   5: aload_0
    //   6: invokevirtual 120	android/view/View:getAlpha	()F
    //   9: fstore_1
    //   10: goto_w 0 0 0 5
    //   15: aload_0
    //   16: ifnull +8 -> 24
    //   19: goto_w 0 0 0 -57
    //   24: goto_w 0 0 0 -68
    //   29: aload_0
    //   30: invokevirtual 127	android/view/View:getParent	()Landroid/view/ViewParent;
    //   33: ifnull +8 -> 41
    //   36: goto_w 0 0 0 -33
    //   41: goto_w 0 0 0 -45
    //   46: fload_1
    //   47: f2d
    //   48: dconst_0
    //   49: dcmpl
    //   50: ifeq +8 -> 58
    //   53: goto_w 0 0 0 -10
    //   58: goto_w 0 0 0 -22
    //   63: aload_0
    //   64: invokevirtual 127	android/view/View:getParent	()Landroid/view/ViewParent;
    //   67: instanceof 42
    //   70: ifeq +8 -> 78
    //   73: goto_w 0 0 1 5
    //   78: goto_w 0 0 0 -6
    //   83: fload_1
    //   84: aload_0
    //   85: invokevirtual 127	android/view/View:getParent	()Landroid/view/ViewParent;
    //   88: checkcast 42	android/view/View
    //   91: invokevirtual 120	android/view/View:getAlpha	()F
    //   94: fmul
    //   95: fstore_1
    //   96: aload_0
    //   97: invokevirtual 127	android/view/View:getParent	()Landroid/view/ViewParent;
    //   100: checkcast 42	android/view/View
    //   103: astore_0
    //   104: goto_w -1 -1 -1 -89
    //   109: fload_1
    //   110: freturn
    //   111: getstatic 93	com/moat/analytics/mobile/kiip/y:ˏॱ	I
    //   114: bipush 115
    //   116: iadd
    //   117: dup
    //   118: sipush 128
    //   121: irem
    //   122: putstatic 89	com/moat/analytics/mobile/kiip/y:ˊॱ	I
    //   125: iconst_2
    //   126: irem
    //   127: ifeq +8 -> 135
    //   130: goto_w 0 0 0 -11
    //   135: goto_w 0 0 0 -23
    //   140: aload_0
    //   141: invokevirtual 127	android/view/View:getParent	()Landroid/view/ViewParent;
    //   144: ifnull +8 -> 152
    //   147: goto_w 0 0 1 12
    //   152: goto_w 0 0 1 0
    //   157: getstatic 89	com/moat/analytics/mobile/kiip/y:ˊॱ	I
    //   160: bipush 63
    //   162: iadd
    //   163: dup
    //   164: sipush 128
    //   167: irem
    //   168: putstatic 93	com/moat/analytics/mobile/kiip/y:ˏॱ	I
    //   171: iconst_2
    //   172: irem
    //   173: ifne +8 -> 181
    //   176: goto_w 0 0 0 10
    //   181: goto_w -1 -1 -1 -98
    //   186: goto_w -1 -1 -1 -103
    //   191: tableswitch	default:+-82->109, 0:+-82->109, 1:+-80->111
    //   212: iconst_0
    //   213: goto_w -1 -1 -1 -22
    //   218: iconst_1
    //   219: goto_w -1 -1 -1 -28
    //   224: lookupswitch	default:+-115->109, 27:+-178->46, 50:+-115->109
    //   252: bipush 50
    //   254: goto_w -1 -1 -1 -30
    //   259: bipush 27
    //   261: goto_w -1 -1 -1 -37
    //   266: lookupswitch	default:+-157->109, 28:+-203->63, 62:+-157->109
    //   292: bipush 62
    //   294: goto_w -1 -1 -1 -28
    //   299: bipush 28
    //   301: goto_w -1 -1 -1 -35
    //   306: tableswitch	default:+-149->157, 0:+-149->157, 1:+-197->109
    //   328: iconst_1
    //   329: goto_w -1 -1 -1 -23
    //   334: iconst_0
    //   335: goto_w -1 -1 -1 -29
    //   340: lookupswitch	default:+-311->29, 1:+-200->140, 80:+-311->29
    //   368: bipush 80
    //   370: goto_w -1 -1 -1 -30
    //   375: bipush 1
    //   377: goto_w -1 -1 -1 -37
    //   382: lookupswitch	default:+-273->109, 49:+-273->109, 58:+-336->46
    //   408: bipush 49
    //   410: goto_w -1 -1 -1 -28
    //   415: bipush 58
    //   417: goto_w -1 -1 -1 -35
    // Line number table:
    //   Java source line #211	-> byte code offset #5
    //   Java source line #212	-> byte code offset #15
    //   Java source line #213	-> byte code offset #46
    //   Java source line #214	-> byte code offset #63
    //   Java source line #215	-> byte code offset #83
    //   Java source line #216	-> byte code offset #96
    //   Java source line #222	-> byte code offset #109
  }
  
  /* Error */
  static Rect ˏ(View arg0)
  {
    // Byte code:
    //   0: goto_w 0 0 0 5
    //   5: aload_0
    //   6: ifnull +8 -> 14
    //   9: goto_w 0 0 0 89
    //   14: goto_w 0 0 0 78
    //   19: aload_0
    //   20: invokestatic 148	com/moat/analytics/mobile/kiip/y:ॱ	(Landroid/view/View;)Landroid/graphics/Rect;
    //   23: areturn
    //   24: new 34	android/graphics/Rect
    //   27: dup
    //   28: iconst_0
    //   29: iconst_0
    //   30: iconst_0
    //   31: iconst_0
    //   32: invokespecial 105	android/graphics/Rect:<init>	(IIII)V
    //   35: areturn
    //   36: getstatic 93	com/moat/analytics/mobile/kiip/y:ˏॱ	I
    //   39: bipush 23
    //   41: iadd
    //   42: dup
    //   43: sipush 128
    //   46: irem
    //   47: putstatic 89	com/moat/analytics/mobile/kiip/y:ˊॱ	I
    //   50: iconst_2
    //   51: irem
    //   52: ifeq +8 -> 60
    //   55: goto_w 0 0 0 10
    //   60: goto_w -1 -1 -1 -41
    //   65: goto_w -1 -1 -1 -46
    //   70: tableswitch	default:+-46->24, 0:+-46->24, 1:+-34->36
    //   92: iconst_0
    //   93: goto_w -1 -1 -1 -23
    //   98: iconst_1
    //   99: goto_w -1 -1 -1 -29
    // Line number table:
    //   Java source line #232	-> byte code offset #5
  }
  
  /* Error */
  private static void ˏ(java.util.ArrayDeque<b> arg0, b arg1, boolean arg2)
  {
    // Byte code:
    //   0: goto_w 0 0 0 5
    //   5: aload_1
    //   6: getfield 99	com/moat/analytics/mobile/kiip/y$b:ˊ	Landroid/view/View;
    //   9: instanceof 43
    //   12: ifeq +8 -> 20
    //   15: goto_w 0 0 0 127
    //   20: goto_w 0 0 0 116
    //   25: aload_1
    //   26: getfield 99	com/moat/analytics/mobile/kiip/y$b:ˊ	Landroid/view/View;
    //   29: instanceof 45
    //   32: ifne +8 -> 40
    //   35: goto_w 0 0 0 -108
    //   40: goto_w 0 0 0 -120
    //   45: aload_1
    //   46: getfield 99	com/moat/analytics/mobile/kiip/y$b:ˊ	Landroid/view/View;
    //   49: checkcast 43	android/view/ViewGroup
    //   52: dup
    //   53: astore_3
    //   54: invokevirtual 135	android/view/ViewGroup:getChildCount	()I
    //   57: iconst_1
    //   58: isub
    //   59: istore 4
    //   61: goto_w 0 0 0 5
    //   66: iload 4
    //   68: iflt +8 -> 76
    //   71: goto_w 0 0 0 10
    //   76: goto_w 0 0 0 38
    //   81: aload_0
    //   82: new 54	com/moat/analytics/mobile/kiip/y$b
    //   85: dup
    //   86: aload_3
    //   87: iload 4
    //   89: invokevirtual 134	android/view/ViewGroup:getChildAt	(I)Landroid/view/View;
    //   92: aload_1
    //   93: getfield 101	com/moat/analytics/mobile/kiip/y$b:ॱ	I
    //   96: iconst_1
    //   97: iadd
    //   98: iload_2
    //   99: invokespecial 151	com/moat/analytics/mobile/kiip/y$b:<init>	(Landroid/view/View;IZ)V
    //   102: invokevirtual 173	java/util/ArrayDeque:add	(Ljava/lang/Object;)Z
    //   105: pop
    //   106: iinc 4 -1
    //   109: goto_w -1 -1 -1 -43
    //   114: return
    //   115: tableswitch	default:+-1->114, 0:+-90->25, 1:+-1->114
    //   136: iconst_1
    //   137: goto_w -1 -1 -1 -22
    //   142: iconst_0
    //   143: goto_w -1 -1 -1 -28
    //   148: lookupswitch	default:+-34->114, 24:+-103->45, 38:+-34->114
    //   176: bipush 38
    //   178: goto_w -1 -1 -1 -30
    //   183: bipush 24
    //   185: goto_w -1 -1 -1 -37
    // Line number table:
    //   Java source line #300	-> byte code offset #5
    //   Java source line #301	-> byte code offset #45
    //   Java source line #302	-> byte code offset #53
    //   Java source line #303	-> byte code offset #57
    //   Java source line #304	-> byte code offset #81
    //   Java source line #303	-> byte code offset #106
  }
  
  /* Error */
  @android.support.annotation.VisibleForTesting
  private static boolean ˏ(Rect arg0, @android.support.annotation.NonNull View arg1, java.util.Set<Rect> arg2)
  {
    // Byte code:
    //   0: goto_w 0 0 0 5
    //   5: iconst_0
    //   6: istore_3
    //   7: iconst_0
    //   8: istore 4
    //   10: aload_1
    //   11: astore 9
    //   13: new 67	java/util/ArrayList
    //   16: dup
    //   17: invokespecial 176	java/util/ArrayList:<init>	()V
    //   20: astore 8
    //   22: aload 9
    //   24: astore 5
    //   26: iconst_0
    //   27: istore 6
    //   29: goto_w 0 0 0 5
    //   34: aload 5
    //   36: invokevirtual 127	android/view/View:getParent	()Landroid/view/ViewParent;
    //   39: ifnonnull +8 -> 47
    //   42: goto_w 0 0 4 4
    //   47: goto_w 0 0 3 -7
    //   52: aload 5
    //   54: aload 9
    //   56: invokevirtual 128	android/view/View:getRootView	()Landroid/view/View;
    //   59: if_acmpne +8 -> 67
    //   62: goto_w 0 0 4 25
    //   67: goto_w 0 0 4 13
    //   72: iinc 6 1
    //   75: iload 6
    //   77: bipush 50
    //   79: if_icmple +8 -> 87
    //   82: goto_w 0 0 4 40
    //   87: goto_w 0 0 4 29
    //   92: aconst_null
    //   93: goto_w 0 0 0 58
    //   98: aload 8
    //   100: iconst_0
    //   101: aload 5
    //   103: invokeinterface 187 3 0
    //   108: aload 5
    //   110: invokevirtual 127	android/view/View:getParent	()Landroid/view/ViewParent;
    //   113: instanceof 42
    //   116: ifeq +8 -> 124
    //   119: goto_w 0 0 4 44
    //   124: goto_w 0 0 4 32
    //   129: aload 5
    //   131: invokevirtual 127	android/view/View:getParent	()Landroid/view/ViewParent;
    //   134: checkcast 42	android/view/View
    //   137: astore 5
    //   139: goto_w -1 -1 -1 -105
    //   144: aload 8
    //   146: goto_w 0 0 0 5
    //   151: dup
    //   152: astore 5
    //   154: ifnull +8 -> 162
    //   157: goto_w 0 0 4 41
    //   162: goto_w 0 0 4 30
    //   167: aload 5
    //   169: invokeinterface 191 1 0
    //   174: ifeq +8 -> 182
    //   177: goto_w 0 0 4 62
    //   182: goto_w 0 0 4 50
    //   187: iconst_0
    //   188: ireturn
    //   189: aload_1
    //   190: invokevirtual 128	android/view/View:getRootView	()Landroid/view/View;
    //   193: astore 6
    //   195: new 66	java/util/ArrayDeque
    //   198: dup
    //   199: invokespecial 172	java/util/ArrayDeque:<init>	()V
    //   202: dup
    //   203: astore 7
    //   205: new 54	com/moat/analytics/mobile/kiip/y$b
    //   208: dup
    //   209: aload 6
    //   211: iconst_0
    //   212: iconst_1
    //   213: invokespecial 151	com/moat/analytics/mobile/kiip/y$b:<init>	(Landroid/view/View;IZ)V
    //   216: invokevirtual 173	java/util/ArrayDeque:add	(Ljava/lang/Object;)Z
    //   219: pop
    //   220: ldc 5
    //   222: aload_1
    //   223: ldc 22
    //   225: invokestatic 136	com/moat/analytics/mobile/kiip/b:ˏ	(Ljava/lang/String;Ljava/lang/Object;Ljava/lang/String;)V
    //   228: goto_w 0 0 0 5
    //   233: aload 7
    //   235: invokevirtual 174	java/util/ArrayDeque:isEmpty	()Z
    //   238: ifne +8 -> 246
    //   241: goto_w 0 0 4 38
    //   246: goto_w 0 0 4 26
    //   251: iload_3
    //   252: sipush 250
    //   255: if_icmpge +8 -> 263
    //   258: goto_w 0 0 4 61
    //   263: goto_w 0 0 4 49
    //   268: iinc 3 1
    //   271: aload 7
    //   273: invokevirtual 175	java/util/ArrayDeque:pollLast	()Ljava/lang/Object;
    //   276: checkcast 54	com/moat/analytics/mobile/kiip/y$b
    //   279: dup
    //   280: astore 6
    //   282: getfield 99	com/moat/analytics/mobile/kiip/y$b:ˊ	Landroid/view/View;
    //   285: aload_1
    //   286: invokevirtual 165	java/lang/Object:equals	(Ljava/lang/Object;)Z
    //   289: ifeq +8 -> 297
    //   292: goto_w 0 0 4 67
    //   297: goto_w 0 0 4 55
    //   302: iconst_1
    //   303: istore 4
    //   305: ldc 5
    //   307: aload_0
    //   308: ldc 10
    //   310: invokestatic 136	com/moat/analytics/mobile/kiip/b:ˏ	(Ljava/lang/String;Ljava/lang/Object;Ljava/lang/String;)V
    //   313: goto_w -1 -1 -1 -80
    //   318: aload 6
    //   320: getfield 100	com/moat/analytics/mobile/kiip/y$b:ˋ	Z
    //   323: ifeq +8 -> 331
    //   326: goto_w 0 0 4 73
    //   331: goto_w 0 0 4 61
    //   336: aload 5
    //   338: aload 6
    //   340: astore 8
    //   342: dup
    //   343: astore 9
    //   345: invokeinterface 193 1 0
    //   350: aload 8
    //   352: getfield 101	com/moat/analytics/mobile/kiip/y$b:ॱ	I
    //   355: if_icmple +8 -> 363
    //   358: goto_w 0 0 4 81
    //   363: goto_w 0 0 4 69
    //   368: aload 9
    //   370: aload 8
    //   372: getfield 101	com/moat/analytics/mobile/kiip/y$b:ॱ	I
    //   375: invokeinterface 190 2 0
    //   380: checkcast 42	android/view/View
    //   383: goto_w 0 0 0 11
    //   388: aconst_null
    //   389: goto_w 0 0 0 5
    //   394: astore 8
    //   396: aload 6
    //   398: getfield 99	com/moat/analytics/mobile/kiip/y$b:ˊ	Landroid/view/View;
    //   401: aload 8
    //   403: if_acmpne +8 -> 411
    //   406: goto_w 0 0 4 73
    //   411: goto_w 0 0 4 61
    //   416: aload 7
    //   418: aload 6
    //   420: iconst_1
    //   421: invokestatic 146	com/moat/analytics/mobile/kiip/y:ˏ	(Ljava/util/ArrayDeque;Lcom/moat/analytics/mobile/kiip/y$b;Z)V
    //   424: goto_w -1 -1 -1 65
    //   429: aload 6
    //   431: getfield 99	com/moat/analytics/mobile/kiip/y$b:ˊ	Landroid/view/View;
    //   434: dup
    //   435: astore 9
    //   437: invokevirtual 133	android/view/View:isShown	()Z
    //   440: ifeq +8 -> 448
    //   443: goto_w 0 0 4 76
    //   448: goto_w 0 0 4 64
    //   453: aload 9
    //   455: invokevirtual 120	android/view/View:getAlpha	()F
    //   458: f2d
    //   459: dconst_0
    //   460: dcmpl
    //   461: ifle +8 -> 469
    //   464: goto_w 0 0 4 90
    //   469: goto_w 0 0 4 79
    //   474: iconst_1
    //   475: goto_w 0 0 0 11
    //   480: iconst_0
    //   481: goto_w 0 0 0 5
    //   486: ifeq +8 -> 494
    //   489: goto_w 0 0 4 106
    //   494: goto_w 0 0 4 94
    //   499: iload 4
    //   501: ifeq +8 -> 509
    //   504: goto_w 0 0 4 -125
    //   509: goto_w 0 0 4 119
    //   514: getstatic 80	android/os/Build$VERSION:SDK_INT	I
    //   517: bipush 21
    //   519: if_icmplt +8 -> 527
    //   522: goto_w 0 0 4 -103
    //   527: goto_w 0 0 4 -115
    //   532: aload 6
    //   534: getfield 99	com/moat/analytics/mobile/kiip/y$b:ˊ	Landroid/view/View;
    //   537: invokevirtual 123	android/view/View:getElevation	()F
    //   540: aload 8
    //   542: invokevirtual 123	android/view/View:getElevation	()F
    //   545: fcmpg
    //   546: ifge +8 -> 554
    //   549: goto_w 0 0 0 10
    //   554: goto_w 0 0 0 55
    //   559: goto_w -1 -1 -2 -70
    //   564: getstatic 80	android/os/Build$VERSION:SDK_INT	I
    //   567: bipush 21
    //   569: if_icmplt +8 -> 577
    //   572: goto_w 0 0 4 -113
    //   577: goto_w 0 0 4 -125
    //   582: aload 6
    //   584: getfield 99	com/moat/analytics/mobile/kiip/y$b:ˊ	Landroid/view/View;
    //   587: invokevirtual 123	android/view/View:getElevation	()F
    //   590: aload 8
    //   592: invokevirtual 123	android/view/View:getElevation	()F
    //   595: fcmpg
    //   596: ifle +8 -> 604
    //   599: goto_w 0 0 4 -100
    //   604: goto_w 0 0 4 -112
    //   609: aload 7
    //   611: aload 6
    //   613: iconst_0
    //   614: invokestatic 146	com/moat/analytics/mobile/kiip/y:ˏ	(Ljava/util/ArrayDeque;Lcom/moat/analytics/mobile/kiip/y$b;Z)V
    //   617: ldc 43
    //   619: aload 6
    //   621: getfield 99	com/moat/analytics/mobile/kiip/y$b:ˊ	Landroid/view/View;
    //   624: invokevirtual 166	java/lang/Object:getClass	()Ljava/lang/Class;
    //   627: invokevirtual 153	java/lang/Class:getSuperclass	()Ljava/lang/Class;
    //   630: invokevirtual 165	java/lang/Object:equals	(Ljava/lang/Object;)Z
    //   633: ifeq +8 -> 641
    //   636: goto_w 0 0 4 -102
    //   641: goto_w 0 0 4 -113
    //   646: getstatic 80	android/os/Build$VERSION:SDK_INT	I
    //   649: bipush 19
    //   651: if_icmplt +8 -> 659
    //   654: goto_w 0 0 4 -79
    //   659: goto_w 0 0 4 -91
    //   664: aload 6
    //   666: getfield 99	com/moat/analytics/mobile/kiip/y$b:ˊ	Landroid/view/View;
    //   669: invokevirtual 121	android/view/View:getBackground	()Landroid/graphics/drawable/Drawable;
    //   672: ifnull +8 -> 680
    //   675: goto_w 0 0 4 -65
    //   680: goto_w 0 0 4 -76
    //   685: aload 6
    //   687: getfield 99	com/moat/analytics/mobile/kiip/y$b:ˊ	Landroid/view/View;
    //   690: invokevirtual 121	android/view/View:getBackground	()Landroid/graphics/drawable/Drawable;
    //   693: invokevirtual 113	android/graphics/drawable/Drawable:getAlpha	()I
    //   696: ifeq +8 -> 704
    //   699: goto_w 0 0 4 -48
    //   704: goto_w 0 0 4 -60
    //   709: aload 6
    //   711: getfield 99	com/moat/analytics/mobile/kiip/y$b:ˊ	Landroid/view/View;
    //   714: invokestatic 148	com/moat/analytics/mobile/kiip/y:ॱ	(Landroid/view/View;)Landroid/graphics/Rect;
    //   717: dup
    //   718: astore 8
    //   720: aload_0
    //   721: aload 8
    //   723: invokevirtual 110	android/graphics/Rect:setIntersect	(Landroid/graphics/Rect;Landroid/graphics/Rect;)Z
    //   726: ifeq +8 -> 734
    //   729: goto_w 0 0 0 10
    //   734: goto_w 0 0 0 84
    //   739: ldc 5
    //   741: aload 6
    //   743: getfield 99	com/moat/analytics/mobile/kiip/y$b:ˊ	Landroid/view/View;
    //   746: new 64	java/lang/StringBuilder
    //   749: dup
    //   750: ldc 4
    //   752: invokespecial 168	java/lang/StringBuilder:<init>	(Ljava/lang/String;)V
    //   755: aload 6
    //   757: getfield 99	com/moat/analytics/mobile/kiip/y$b:ˊ	Landroid/view/View;
    //   760: invokevirtual 166	java/lang/Object:getClass	()Ljava/lang/Class;
    //   763: invokevirtual 152	java/lang/Class:getSimpleName	()Ljava/lang/String;
    //   766: invokevirtual 169	java/lang/StringBuilder:append	(Ljava/lang/String;)Ljava/lang/StringBuilder;
    //   769: ldc 2
    //   771: invokevirtual 169	java/lang/StringBuilder:append	(Ljava/lang/String;)Ljava/lang/StringBuilder;
    //   774: aload 8
    //   776: invokevirtual 111	android/graphics/Rect:toString	()Ljava/lang/String;
    //   779: invokevirtual 169	java/lang/StringBuilder:append	(Ljava/lang/String;)Ljava/lang/StringBuilder;
    //   782: invokevirtual 170	java/lang/StringBuilder:toString	()Ljava/lang/String;
    //   785: invokestatic 136	com/moat/analytics/mobile/kiip/b:ˏ	(Ljava/lang/String;Ljava/lang/Object;Ljava/lang/String;)V
    //   788: aload_2
    //   789: aload 8
    //   791: invokeinterface 196 2 0
    //   796: pop
    //   797: aload 8
    //   799: aload_0
    //   800: invokevirtual 106	android/graphics/Rect:contains	(Landroid/graphics/Rect;)Z
    //   803: ifeq +8 -> 811
    //   806: goto_w 0 0 4 -120
    //   811: goto_w 0 0 4 125
    //   816: iconst_1
    //   817: ireturn
    //   818: goto_w -1 -1 -3 -73
    //   823: goto_w 0 0 0 13
    //   828: invokestatic 140	com/moat/analytics/mobile/kiip/o:ॱ	(Ljava/lang/Exception;)V
    //   831: goto_w 0 0 0 5
    //   836: iconst_0
    //   837: ireturn
    //   838: getstatic 93	com/moat/analytics/mobile/kiip/y:ˏॱ	I
    //   841: bipush 83
    //   843: iadd
    //   844: dup
    //   845: sipush 128
    //   848: irem
    //   849: putstatic 89	com/moat/analytics/mobile/kiip/y:ˊॱ	I
    //   852: iconst_2
    //   853: irem
    //   854: ifeq +8 -> 862
    //   857: goto_w 0 0 0 10
    //   862: goto_w -1 -1 -3 35
    //   867: goto_w -1 -1 -3 30
    //   872: getstatic 89	com/moat/analytics/mobile/kiip/y:ˊॱ	I
    //   875: bipush 117
    //   877: iadd
    //   878: dup
    //   879: sipush 128
    //   882: irem
    //   883: putstatic 93	com/moat/analytics/mobile/kiip/y:ˏॱ	I
    //   886: iconst_2
    //   887: irem
    //   888: ifne +8 -> 896
    //   891: goto_w 0 0 0 10
    //   896: goto_w -1 -1 -3 -16
    //   901: goto_w -1 -1 -3 -21
    //   906: getstatic 89	com/moat/analytics/mobile/kiip/y:ˊॱ	I
    //   909: bipush 7
    //   911: iadd
    //   912: dup
    //   913: sipush 128
    //   916: irem
    //   917: putstatic 93	com/moat/analytics/mobile/kiip/y:ˏॱ	I
    //   920: iconst_2
    //   921: irem
    //   922: ifne +8 -> 930
    //   925: goto_w 0 0 0 10
    //   930: goto_w -1 -1 -2 81
    //   935: goto_w -1 -1 -2 76
    //   940: getstatic 89	com/moat/analytics/mobile/kiip/y:ˊॱ	I
    //   943: bipush 1
    //   945: iadd
    //   946: dup
    //   947: sipush 128
    //   950: irem
    //   951: putstatic 93	com/moat/analytics/mobile/kiip/y:ˏॱ	I
    //   954: iconst_2
    //   955: irem
    //   956: ifne +8 -> 964
    //   959: goto_w 0 0 0 10
    //   964: goto_w -1 -1 -2 -126
    //   969: goto_w -1 -1 -2 125
    //   974: getstatic 89	com/moat/analytics/mobile/kiip/y:ˊॱ	I
    //   977: bipush 77
    //   979: iadd
    //   980: dup
    //   981: sipush 128
    //   984: irem
    //   985: putstatic 93	com/moat/analytics/mobile/kiip/y:ˏॱ	I
    //   988: iconst_2
    //   989: irem
    //   990: ifne +8 -> 998
    //   993: goto_w 0 0 0 10
    //   998: goto_w -1 -1 -2 -78
    //   1003: goto_w -1 -1 -2 -83
    //   1008: getstatic 89	com/moat/analytics/mobile/kiip/y:ˊॱ	I
    //   1011: bipush 125
    //   1013: iadd
    //   1014: dup
    //   1015: sipush 128
    //   1018: irem
    //   1019: putstatic 93	com/moat/analytics/mobile/kiip/y:ˏॱ	I
    //   1022: iconst_2
    //   1023: irem
    //   1024: ifne +8 -> 1032
    //   1027: goto_w 0 0 0 10
    //   1032: goto_w -1 -1 -1 40
    //   1037: goto_w -1 -1 -1 35
    //   1042: tableswitch	default:+-990->52, 0:+-990->52, 1:+-970->72
    //   1064: iconst_1
    //   1065: goto_w -1 -1 -1 -23
    //   1070: iconst_0
    //   1071: goto_w -1 -1 -1 -29
    //   1076: lookupswitch	default:+-1004->72, 16:+-932->144, 60:+-1004->72
    //   1104: bipush 16
    //   1106: goto_w -1 -1 -1 -30
    //   1111: bipush 60
    //   1113: goto_w -1 -1 -1 -37
    //   1118: tableswitch	default:+-1026->92, 0:+-1020->98, 1:+-1026->92
    //   1140: iconst_0
    //   1141: goto_w -1 -1 -1 -23
    //   1146: iconst_1
    //   1147: goto_w -1 -1 -1 -29
    //   1152: lookupswitch	default:+-314->838, 81:+-1008->144, 97:+-314->838
    //   1180: bipush 81
    //   1182: goto_w -1 -1 -1 -30
    //   1187: bipush 97
    //   1189: goto_w -1 -1 -1 -37
    //   1194: tableswitch	default:+-1007->187, 0:+-1007->187, 1:+-1027->167
    //   1216: iconst_0
    //   1217: goto_w -1 -1 -1 -23
    //   1222: iconst_1
    //   1223: goto_w -1 -1 -1 -29
    //   1228: lookupswitch	default:+-1041->187, 50:+-1041->187, 63:+-1039->189
    //   1256: bipush 63
    //   1258: goto_w -1 -1 -1 -30
    //   1263: bipush 50
    //   1265: goto_w -1 -1 -1 -37
    //   1270: lookupswitch	default:+-1019->251, 69:+-447->823, 75:+-1019->251
    //   1296: bipush 69
    //   1298: goto_w -1 -1 -1 -28
    //   1303: bipush 75
    //   1305: goto_w -1 -1 -1 -35
    //   1310: lookupswitch	default:+-1042->268, 2:+-487->823, 18:+-1042->268
    //   1336: bipush 2
    //   1338: goto_w -1 -1 -1 -28
    //   1343: bipush 18
    //   1345: goto_w -1 -1 -1 -35
    //   1350: lookupswitch	default:+-1048->302, 29:+-1048->302, 47:+-1032->318
    //   1376: bipush 47
    //   1378: goto_w -1 -1 -1 -28
    //   1383: bipush 29
    //   1385: goto_w -1 -1 -1 -35
    //   1390: lookupswitch	default:+-1054->336, 31:+-1054->336, 55:+-781->609
    //   1416: bipush 55
    //   1418: goto_w -1 -1 -1 -28
    //   1423: bipush 31
    //   1425: goto_w -1 -1 -1 -35
    //   1430: lookupswitch	default:+-1042->388, 36:+-1042->388, 94:+-558->872
    //   1456: bipush 36
    //   1458: goto_w -1 -1 -1 -28
    //   1463: bipush 94
    //   1465: goto_w -1 -1 -1 -35
    //   1470: lookupswitch	default:+-1041->429, 59:+-1054->416, 83:+-1041->429
    //   1496: bipush 83
    //   1498: goto_w -1 -1 -1 -28
    //   1503: bipush 59
    //   1505: goto_w -1 -1 -1 -35
    //   1510: lookupswitch	default:+-1057->453, 11:+-1057->453, 57:+-1030->480
    //   1536: bipush 57
    //   1538: goto_w -1 -1 -1 -28
    //   1543: bipush 11
    //   1545: goto_w -1 -1 -1 -35
    //   1550: tableswitch	default:+-1076->474, 0:+-1070->480, 1:+-1076->474
    //   1572: iconst_0
    //   1573: goto_w -1 -1 -1 -23
    //   1578: iconst_1
    //   1579: goto_w -1 -1 -1 -29
    //   1584: lookupswitch	default:+-1351->233, 46:+-1351->233, 67:+-678->906
    //   1612: bipush 46
    //   1614: goto_w -1 -1 -1 -30
    //   1619: bipush 67
    //   1621: goto_w -1 -1 -1 -37
    //   1626: lookupswitch	default:+-1062->564, 29:+-1062->564, 92:+-1112->514
    //   1652: bipush 29
    //   1654: goto_w -1 -1 -1 -28
    //   1659: bipush 92
    //   1661: goto_w -1 -1 -1 -35
    //   1666: lookupswitch	default:+-1134->532, 65:+-1134->532, 68:+-1057->609
    //   1692: bipush 68
    //   1694: goto_w -1 -1 -1 -28
    //   1699: bipush 65
    //   1701: goto_w -1 -1 -1 -35
    //   1706: lookupswitch	default:+-766->940, 32:+-1473->233, 68:+-766->940
    //   1732: bipush 32
    //   1734: goto_w -1 -1 -1 -28
    //   1739: bipush 68
    //   1741: goto_w -1 -1 -1 -35
    //   1746: lookupswitch	default:+-1137->609, 18:+-1137->609, 40:+-1513->233
    //   1772: bipush 40
    //   1774: goto_w -1 -1 -1 -28
    //   1779: bipush 18
    //   1781: goto_w -1 -1 -1 -35
    //   1786: tableswitch	default:+-1077->709, 0:+-1077->709, 1:+-1140->646
    //   1808: iconst_0
    //   1809: goto_w -1 -1 -1 -23
    //   1814: iconst_1
    //   1815: goto_w -1 -1 -1 -29
    //   1820: lookupswitch	default:+-846->974, 2:+-1587->233, 36:+-846->974
    //   1848: bipush 2
    //   1850: goto_w -1 -1 -1 -30
    //   1855: bipush 36
    //   1857: goto_w -1 -1 -1 -37
    //   1862: tableswitch	default:+-1629->233, 0:+-1177->685, 1:+-1629->233
    //   1884: iconst_1
    //   1885: goto_w -1 -1 -1 -23
    //   1890: iconst_0
    //   1891: goto_w -1 -1 -1 -29
    //   1896: lookupswitch	default:+-1663->233, 85:+-1663->233, 92:+-1187->709
    //   1924: bipush 85
    //   1926: goto_w -1 -1 -1 -30
    //   1931: bipush 92
    //   1933: goto_w -1 -1 -1 -37
    //   1938: tableswitch	default:+-1120->818, 0:+-930->1008, 1:+-1120->818
    //   1960: iconst_1
    //   1961: goto_w -1 -1 -1 -23
    //   1966: iconst_0
    //   1967: goto_w -1 -1 -1 -29
    // Line number table:
    //   Java source line #319	-> byte code offset #5
    //   Java source line #320	-> byte code offset #7
    //   Java source line #321	-> byte code offset #10
    //   Java source line #7282	-> byte code offset #13
    //   Java source line #7283	-> byte code offset #22
    //   Java source line #7284	-> byte code offset #26
    //   Java source line #7285	-> byte code offset #34
    //   Java source line #7286	-> byte code offset #72
    //   Java source line #7287	-> byte code offset #75
    //   Java source line #7288	-> byte code offset #98
    //   Java source line #7289	-> byte code offset #108
    //   Java source line #7290	-> byte code offset #129
    //   Java source line #7296	-> byte code offset #144
    //   Java source line #321	-> byte code offset #151
    //   Java source line #323	-> byte code offset #152
    //   Java source line #324	-> byte code offset #187
    //   Java source line #327	-> byte code offset #189
    //   Java source line #328	-> byte code offset #195
    //   Java source line #329	-> byte code offset #203
    //   Java source line #330	-> byte code offset #220
    //   Java source line #332	-> byte code offset #233
    //   Java source line #333	-> byte code offset #251
    //   Java source line #334	-> byte code offset #268
    //   Java source line #335	-> byte code offset #271
    //   Java source line #337	-> byte code offset #280
    //   Java source line #338	-> byte code offset #302
    //   Java source line #339	-> byte code offset #305
    //   Java source line #345	-> byte code offset #318
    //   Java source line #347	-> byte code offset #336
    //   Java source line #7310	-> byte code offset #343
    //   Java source line #7311	-> byte code offset #368
    //   Java source line #7313	-> byte code offset #388
    //   Java source line #347	-> byte code offset #394
    //   Java source line #348	-> byte code offset #396
    //   Java source line #349	-> byte code offset #416
    //   Java source line #354	-> byte code offset #429
    //   Java source line #8272	-> byte code offset #435
    //   Java source line #358	-> byte code offset #499
    //   Java source line #359	-> byte code offset #514
    //   Java source line #360	-> byte code offset #537
    //   Java source line #364	-> byte code offset #564
    //   Java source line #367	-> byte code offset #582
    //   Java source line #377	-> byte code offset #609
    //   Java source line #381	-> byte code offset #617
    //   Java source line #382	-> byte code offset #646
    //   Java source line #383	-> byte code offset #664
    //   Java source line #392	-> byte code offset #709
    //   Java source line #393	-> byte code offset #718
    //   Java source line #394	-> byte code offset #739
    //   Java source line #395	-> byte code offset #788
    //   Java source line #396	-> byte code offset #797
    //   Java source line #397	-> byte code offset #816
    //   Java source line #402	-> byte code offset #828
    //   Java source line #404	-> byte code offset #836
    // Exception table:
    //   from	to	target	type
    //   5	34	828	java/lang/Exception
    //   34	52	828	java/lang/Exception
    //   52	72	828	java/lang/Exception
    //   72	92	828	java/lang/Exception
    //   92	98	828	java/lang/Exception
    //   98	129	828	java/lang/Exception
    //   129	144	828	java/lang/Exception
    //   144	151	828	java/lang/Exception
    //   151	167	828	java/lang/Exception
    //   167	187	828	java/lang/Exception
    //   187	189	828	java/lang/Exception
    //   189	233	828	java/lang/Exception
    //   233	251	828	java/lang/Exception
    //   251	268	828	java/lang/Exception
    //   268	302	828	java/lang/Exception
    //   302	318	828	java/lang/Exception
    //   318	336	828	java/lang/Exception
    //   336	368	828	java/lang/Exception
    //   368	388	828	java/lang/Exception
    //   388	394	828	java/lang/Exception
    //   394	416	828	java/lang/Exception
    //   416	429	828	java/lang/Exception
    //   429	453	828	java/lang/Exception
    //   453	474	828	java/lang/Exception
    //   474	480	828	java/lang/Exception
    //   480	486	828	java/lang/Exception
    //   486	499	828	java/lang/Exception
    //   499	514	828	java/lang/Exception
    //   514	532	828	java/lang/Exception
    //   532	559	828	java/lang/Exception
    //   559	564	828	java/lang/Exception
    //   564	582	828	java/lang/Exception
    //   582	609	828	java/lang/Exception
    //   609	646	828	java/lang/Exception
    //   646	664	828	java/lang/Exception
    //   664	685	828	java/lang/Exception
    //   685	709	828	java/lang/Exception
    //   709	739	828	java/lang/Exception
    //   739	816	828	java/lang/Exception
    //   816	818	828	java/lang/Exception
  }
  
  /* Error */
  @android.support.annotation.VisibleForTesting
  private static int ˊ(Rect arg0, java.util.Set<Rect> arg1)
  {
    // Byte code:
    //   0: goto_w 0 0 0 5
    //   5: iconst_0
    //   6: istore_2
    //   7: aload_1
    //   8: invokeinterface 197 1 0
    //   13: ifne +8 -> 21
    //   16: goto_w 0 0 0 10
    //   21: goto_w 0 0 1 -110
    //   26: new 67	java/util/ArrayList
    //   29: dup
    //   30: invokespecial 176	java/util/ArrayList:<init>	()V
    //   33: dup
    //   34: astore_3
    //   35: aload_1
    //   36: invokeinterface 189 2 0
    //   41: pop
    //   42: aload_3
    //   43: new 52	com/moat/analytics/mobile/kiip/y$2
    //   46: dup
    //   47: invokespecial 149	com/moat/analytics/mobile/kiip/y$2:<init>	()V
    //   50: invokestatic 178	java/util/Collections:sort	(Ljava/util/List;Ljava/util/Comparator;)V
    //   53: new 67	java/util/ArrayList
    //   56: dup
    //   57: invokespecial 176	java/util/ArrayList:<init>	()V
    //   60: astore_1
    //   61: aload_3
    //   62: invokeinterface 192 1 0
    //   67: astore 4
    //   69: goto_w 0 0 0 5
    //   74: aload 4
    //   76: invokeinterface 185 1 0
    //   81: ifeq +8 -> 89
    //   84: goto_w 0 0 1 -78
    //   89: goto_w 0 0 1 -89
    //   94: aload 4
    //   96: invokeinterface 186 1 0
    //   101: checkcast 34	android/graphics/Rect
    //   104: astore 5
    //   106: aload_1
    //   107: aload 5
    //   109: getfield 77	android/graphics/Rect:left	I
    //   112: invokestatic 160	java/lang/Integer:valueOf	(I)Ljava/lang/Integer;
    //   115: invokeinterface 188 2 0
    //   120: pop
    //   121: aload_1
    //   122: aload 5
    //   124: getfield 78	android/graphics/Rect:right	I
    //   127: invokestatic 160	java/lang/Integer:valueOf	(I)Ljava/lang/Integer;
    //   130: invokeinterface 188 2 0
    //   135: pop
    //   136: goto_w -1 -1 -1 -62
    //   141: aload_1
    //   142: invokestatic 177	java/util/Collections:sort	(Ljava/util/List;)V
    //   145: iconst_0
    //   146: istore 4
    //   148: goto_w 0 0 0 5
    //   153: iload 4
    //   155: aload_1
    //   156: invokeinterface 193 1 0
    //   161: iconst_1
    //   162: isub
    //   163: if_icmpge +8 -> 171
    //   166: goto_w 0 0 1 -124
    //   171: goto_w 0 0 1 121
    //   176: aload_1
    //   177: iload 4
    //   179: invokeinterface 190 2 0
    //   184: checkcast 59	java/lang/Integer
    //   187: aload_1
    //   188: iload 4
    //   190: iconst_1
    //   191: iadd
    //   192: invokeinterface 190 2 0
    //   197: invokevirtual 158	java/lang/Integer:equals	(Ljava/lang/Object;)Z
    //   200: ifne +8 -> 208
    //   203: goto_w 0 0 1 -120
    //   208: goto_w 0 0 1 124
    //   213: new 34	android/graphics/Rect
    //   216: dup
    //   217: aload_1
    //   218: iload 4
    //   220: invokeinterface 190 2 0
    //   225: checkcast 59	java/lang/Integer
    //   228: invokevirtual 159	java/lang/Integer:intValue	()I
    //   231: aload_0
    //   232: getfield 79	android/graphics/Rect:top	I
    //   235: aload_1
    //   236: iload 4
    //   238: iconst_1
    //   239: iadd
    //   240: invokeinterface 190 2 0
    //   245: checkcast 59	java/lang/Integer
    //   248: invokevirtual 159	java/lang/Integer:intValue	()I
    //   251: aload_0
    //   252: getfield 76	android/graphics/Rect:bottom	I
    //   255: invokespecial 105	android/graphics/Rect:<init>	(IIII)V
    //   258: astore 5
    //   260: aload_0
    //   261: getfield 79	android/graphics/Rect:top	I
    //   264: istore 6
    //   266: aload_3
    //   267: invokeinterface 192 1 0
    //   272: astore 7
    //   274: goto_w 0 0 0 5
    //   279: aload 7
    //   281: invokeinterface 185 1 0
    //   286: ifeq +8 -> 294
    //   289: goto_w 0 0 1 90
    //   294: goto_w 0 0 1 78
    //   299: aload 7
    //   301: invokeinterface 186 1 0
    //   306: checkcast 34	android/graphics/Rect
    //   309: dup
    //   310: astore 8
    //   312: aload 5
    //   314: invokestatic 109	android/graphics/Rect:intersects	(Landroid/graphics/Rect;Landroid/graphics/Rect;)Z
    //   317: ifeq +8 -> 325
    //   320: goto_w 0 0 1 99
    //   325: goto_w 0 0 1 87
    //   330: aload 8
    //   332: getfield 76	android/graphics/Rect:bottom	I
    //   335: iload 6
    //   337: if_icmple +8 -> 345
    //   340: goto_w 0 0 1 114
    //   345: goto_w 0 0 1 103
    //   350: iload_2
    //   351: aload 5
    //   353: invokevirtual 112	android/graphics/Rect:width	()I
    //   356: aload 8
    //   358: getfield 76	android/graphics/Rect:bottom	I
    //   361: iload 6
    //   363: aload 8
    //   365: getfield 79	android/graphics/Rect:top	I
    //   368: invokestatic 162	java/lang/Math:max	(II)I
    //   371: isub
    //   372: imul
    //   373: iadd
    //   374: istore_2
    //   375: aload 8
    //   377: getfield 76	android/graphics/Rect:bottom	I
    //   380: istore 6
    //   382: goto_w 0 0 0 5
    //   387: aload 8
    //   389: getfield 76	android/graphics/Rect:bottom	I
    //   392: aload 5
    //   394: getfield 76	android/graphics/Rect:bottom	I
    //   397: if_icmpeq +8 -> 405
    //   400: goto_w 0 0 0 10
    //   405: goto_w 0 0 0 10
    //   410: goto_w -1 -1 -1 125
    //   415: iinc 4 1
    //   418: goto_w -1 -1 -2 -9
    //   423: iload_2
    //   424: ireturn
    //   425: getstatic 93	com/moat/analytics/mobile/kiip/y:ˏॱ	I
    //   428: bipush 59
    //   430: iadd
    //   431: dup
    //   432: sipush 128
    //   435: irem
    //   436: putstatic 89	com/moat/analytics/mobile/kiip/y:ˊॱ	I
    //   439: iconst_2
    //   440: irem
    //   441: ifeq +8 -> 449
    //   444: goto_w 0 0 1 46
    //   449: goto_w 0 0 1 35
    //   454: aload_1
    //   455: iload 4
    //   457: invokeinterface 190 2 0
    //   462: checkcast 59	java/lang/Integer
    //   465: aload_1
    //   466: iload 4
    //   468: iconst_1
    //   469: iadd
    //   470: invokeinterface 190 2 0
    //   475: invokevirtual 158	java/lang/Integer:equals	(Ljava/lang/Object;)Z
    //   478: ifne +8 -> 486
    //   481: goto_w 0 0 1 50
    //   486: goto_w 0 0 1 38
    //   491: tableswitch	default:+-397->94, 0:+-350->141, 1:+-397->94
    //   512: iconst_0
    //   513: goto_w -1 -1 -1 -22
    //   518: iconst_1
    //   519: goto_w -1 -1 -1 -28
    //   524: tableswitch	default:+-101->423, 0:+-101->423, 1:+-99->425
    //   548: iconst_0
    //   549: goto_w -1 -1 -1 -25
    //   554: iconst_1
    //   555: goto_w -1 -1 -1 -31
    //   560: lookupswitch	default:+-145->415, 36:+-347->213, 67:+-145->415
    //   588: bipush 67
    //   590: goto_w -1 -1 -1 -30
    //   595: bipush 36
    //   597: goto_w -1 -1 -1 -37
    //   602: lookupswitch	default:+-187->415, 44:+-187->415, 82:+-303->299
    //   628: bipush 44
    //   630: goto_w -1 -1 -1 -28
    //   635: bipush 82
    //   637: goto_w -1 -1 -1 -35
    //   642: lookupswitch	default:+-232->410, 61:+-312->330, 76:+-232->410
    //   668: bipush 76
    //   670: goto_w -1 -1 -1 -28
    //   675: bipush 61
    //   677: goto_w -1 -1 -1 -35
    //   682: tableswitch	default:+-295->387, 0:+-295->387, 1:+-332->350
    //   704: iconst_0
    //   705: goto_w -1 -1 -1 -23
    //   710: iconst_1
    //   711: goto_w -1 -1 -1 -29
    //   716: tableswitch	default:+-262->454, 0:+-540->176, 1:+-262->454
    //   740: iconst_0
    //   741: goto_w -1 -1 -1 -25
    //   746: iconst_1
    //   747: goto_w -1 -1 -1 -31
    //   752: lookupswitch	default:+-337->415, 25:+-337->415, 35:+-539->213
    //   780: bipush 25
    //   782: goto_w -1 -1 -1 -30
    //   787: bipush 35
    //   789: goto_w -1 -1 -1 -37
    // Line number table:
    //   Java source line #416	-> byte code offset #5
    //   Java source line #417	-> byte code offset #7
    //   Java source line #418	-> byte code offset #26
    //   Java source line #419	-> byte code offset #34
    //   Java source line #421	-> byte code offset #42
    //   Java source line #428	-> byte code offset #53
    //   Java source line #429	-> byte code offset #61
    //   Java source line #430	-> byte code offset #106
    //   Java source line #431	-> byte code offset #121
    //   Java source line #433	-> byte code offset #141
    //   Java source line #434	-> byte code offset #145
    //   Java source line #435	-> byte code offset #176
    //   Java source line #436	-> byte code offset #213
    //   Java source line #437	-> byte code offset #260
    //   Java source line #438	-> byte code offset #266
    //   Java source line #439	-> byte code offset #310
    //   Java source line #440	-> byte code offset #330
    //   Java source line #441	-> byte code offset #350
    //   Java source line #442	-> byte code offset #375
    //   Java source line #444	-> byte code offset #387
    //   Java source line #434	-> byte code offset #415
    //   Java source line #451	-> byte code offset #423
    //   Java source line #435	-> byte code offset #454
  }
  
  static class a
  {
    Rect ˊ;
    double ˋ;
    double ˎ;
    
    a()
    {
      ˊ = new Rect(0, 0, 0, 0);
      ˋ = 0.0D;
      ˎ = 0.0D;
    }
  }
  

  static class b
  {
    final View ˊ;
    
    final int ॱ;
    final boolean ˋ;
    
    b(View paramView, int paramInt, boolean paramBoolean)
    {
      ˊ = paramView;
      ॱ = paramInt;
      ˋ = paramBoolean;
    }
  }
  








  private Map<String, Object> ʼ = new HashMap();
  String ˎ = "{}";
  


  private a ˊ = new a();
  


































  private JSONObject ˏ;
  


































  private Rect ˋ;
  


































  private Rect ॱ;
  

































  private JSONObject ᐝ;
  

































  private JSONObject ʽ;
  

































  private Location ʻ;
  

































  private static int ˊॱ = 0;
  

































  private static int ˏॱ = 1;
  


































  private static Map<String, String> ॱ(Rect paramRect)
  {
    HashMap localHashMap;
    

































    (localHashMap = new HashMap()).put("x", String.valueOf(left));
    localHashMap.put("y", String.valueOf(top));
    localHashMap.put("w", String.valueOf(right - left));
    localHashMap.put("h", String.valueOf(bottom - top));
    return localHashMap;
  }
  
  /* Error */
  private static Rect ˎ(Rect arg0, android.util.DisplayMetrics arg1)
  {
    // Byte code:
    //   0: goto_w 0 0 0 5
    //   5: aload_1
    //   6: getfield 81	android/util/DisplayMetrics:density	F
    //   9: dup
    //   10: fstore_1
    //   11: fconst_0
    //   12: fcmpl
    //   13: ifne +8 -> 21
    //   16: goto_w 0 0 0 -121
    //   21: goto_w 0 0 0 123
    //   26: aload_0
    //   27: areturn
    //   28: aload_0
    //   29: getfield 77	android/graphics/Rect:left	I
    //   32: i2f
    //   33: fload_1
    //   34: fdiv
    //   35: invokestatic 163	java/lang/Math:round	(F)I
    //   38: istore_2
    //   39: aload_0
    //   40: getfield 78	android/graphics/Rect:right	I
    //   43: i2f
    //   44: fload_1
    //   45: fdiv
    //   46: invokestatic 163	java/lang/Math:round	(F)I
    //   49: istore_3
    //   50: aload_0
    //   51: getfield 79	android/graphics/Rect:top	I
    //   54: i2f
    //   55: fload_1
    //   56: fdiv
    //   57: invokestatic 163	java/lang/Math:round	(F)I
    //   60: istore 4
    //   62: aload_0
    //   63: getfield 76	android/graphics/Rect:bottom	I
    //   66: i2f
    //   67: fload_1
    //   68: fdiv
    //   69: invokestatic 163	java/lang/Math:round	(F)I
    //   72: istore_0
    //   73: new 34	android/graphics/Rect
    //   76: dup
    //   77: iload_2
    //   78: iload 4
    //   80: iload_3
    //   81: iload_0
    //   82: invokespecial 105	android/graphics/Rect:<init>	(IIII)V
    //   85: areturn
    //   86: getstatic 93	com/moat/analytics/mobile/kiip/y:ˏॱ	I
    //   89: bipush 75
    //   91: iadd
    //   92: dup
    //   93: sipush 128
    //   96: irem
    //   97: putstatic 89	com/moat/analytics/mobile/kiip/y:ˊॱ	I
    //   100: iconst_2
    //   101: irem
    //   102: ifeq +8 -> 110
    //   105: goto_w 0 0 0 86
    //   110: goto_w 0 0 0 74
    //   115: aload_0
    //   116: areturn
    //   117: lookupswitch	default:+-89->28, 25:+-89->28, 77:+-31->86
    //   144: bipush 25
    //   146: goto_w -1 -1 -1 -29
    //   151: bipush 77
    //   153: goto_w -1 -1 -1 -36
    //   158: lookupswitch	default:+-43->115, 17:+-43->115, 89:+-132->26
    //   184: bipush 89
    //   186: goto_w -1 -1 -1 -28
    //   191: bipush 17
    //   193: goto_w -1 -1 -1 -35
    // Line number table:
    //   Java source line #473	-> byte code offset #5
    //   Java source line #474	-> byte code offset #10
    //   Java source line #475	-> byte code offset #26
    //   Java source line #477	-> byte code offset #28
    //   Java source line #478	-> byte code offset #39
    //   Java source line #479	-> byte code offset #50
    //   Java source line #480	-> byte code offset #62
    //   Java source line #481	-> byte code offset #73
    //   Java source line #475	-> byte code offset #115
  }
  
  private static Rect ॱ(View paramView)
  {
    int[] arrayOfInt = { Integer.MIN_VALUE, Integer.MIN_VALUE };
    paramView.getLocationInWindow(arrayOfInt);
    int j = arrayOfInt[0];
    int i = arrayOfInt[1];
    return new Rect(j, i, j + paramView.getWidth(), i + paramView.getHeight());
  }
}
